{"assets":[],"layers":[{"ddd":0,"ind":0,"ty":4,"nm":"2 line 18","ks":{"o":{"k":100},"r":{"k":55},"p":{"k":[234,222,0]},"a":{"k":[26.925,-303.298,0]},"s":{"k":[100,100,100]}},"ao":0,"shapes":[{"ty":"gr","it":[{"ind":0,"ty":"sh","ks":{"k":{"i":[[0,0],[0,0]],"o":[[0,0],[0,0]],"v":[[39.842,-313.481],[0.942,-304.095]],"c":false}},"nm":"Path 1","mn":"ADBE Vector Shape - Group"},{"ty":"tm","s":{"k":[{"i":{"x":[0.667],"y":[1]},"o":{"x":[1],"y":[0]},"n":["0p667_1_1_0"],"t":49,"s":[100],"e":[0]},{"t":55.0537109375}],"ix":1},"e":{"k":100,"ix":2},"o":{"k":0,"ix":3},"m":1,"ix":2,"nm":"Trim Paths 1","mn":"ADBE Vector Filter - Trim"},{"ty":"st","fillEnabled":true,"c":{"k":[1,1,1,1]},"o":{"k":100},"w":{"k":2},"lc":1,"lj":1,"ml":4,"nm":"Stroke 1","mn":"ADBE Vector Graphic - Stroke"},{"ty":"fl","fillEnabled":true,"c":{"k":[1,1,1,1]},"o":{"k":100},"nm":"Fill 1","mn":"ADBE Vector Graphic - Fill"},{"ty":"tr","p":{"k":[-7.25,-374.5],"ix":2},"a":{"k":[-7.25,-374.5],"ix":1},"s":{"k":[100,100],"ix":3},"r":{"k":0,"ix":6},"o":{"k":100,"ix":7},"sk":{"k":0,"ix":4},"sa":{"k":0,"ix":5},"nm":"Transform"}],"nm":"Shape 1","np":4,"mn":"ADBE Vector Group"},{"ind":1,"ty":"sh","ks":{"k":{"i":[[0,0],[0,0]],"o":[[0,0],[0,0]],"v":[[0,0],[0,0]],"c":false}},"nm":"Path 1","mn":"ADBE Vector Shape - Group"},{"ty":"st","fillEnabled":true,"c":{"k":[1,1,1,1]},"o":{"k":100},"w":{"k":2},"lc":1,"lj":1,"ml":4,"nm":"Stroke 1","mn":"ADBE Vector Graphic - Stroke"}],"ip":0,"op":60,"st":0,"bm":0,"sr":1},{"ddd":0,"ind":1,"ty":4,"nm":"21","ks":{"o":{"k":100},"r":{"k":0},"p":{"k":[249.375,226.5,0]},"a":{"k":[0,0,0]},"s":{"k":[{"i":{"x":[0.667,0.667,0.667],"y":[1,1,0.667]},"o":{"x":[0.333,0.333,0.333],"y":[0,0,0.333]},"n":["0p667_1_0p333_0","0p667_1_0p333_0","0p667_0p667_0p333_0p333"],"t":55,"s":[0,0,100],"e":[139,139,100]},{"t":61.0537109375}]}},"ao":0,"shapes":[{"d":1,"ty":"el","s":{"k":[16,16]},"p":{"k":[0,0]},"nm":"Ellipse Path 1","mn":"ADBE Vector Shape - Ellipse"},{"ty":"fl","fillEnabled":true,"c":{"k":[1,1,1,1]},"o":{"k":100},"nm":"Fill 1","mn":"ADBE Vector Graphic - Fill"}],"ip":0,"op":60,"st":0,"bm":0,"sr":1},{"ddd":0,"ind":2,"ty":4,"nm":"main stroke","ks":{"o":{"k":93.628},"r":{"k":19},"p":{"k":[135,136,0]},"a":{"k":[0,0,0]},"s":{"k":[102,102,100]}},"ao":0,"shapes":[{"ty":"sr","sy":1,"d":1,"pt":{"k":10,"ix":3},"p":{"k":[0,0],"ix":4},"r":{"k":0,"ix":5},"ir":{"k":96,"ix":6},"is":{"k":0,"ix":8},"or":{"k":100,"ix":7},"os":{"k":0,"ix":9},"ix":1,"nm":"Polystar Path 1","mn":"ADBE Vector Shape - Star"},{"ty":"tm","s":{"k":[{"i":{"x":[0],"y":[1]},"o":{"x":[0.333],"y":[0]},"n":["0_1_0p333_0"],"t":25,"s":[29],"e":[0]},{"t":49}],"ix":1},"e":{"k":[{"i":{"x":[0],"y":[1]},"o":{"x":[0.333],"y":[0]},"n":["0_1_0p333_0"],"t":25,"s":[31],"e":[99]},{"t":49}],"ix":2},"o":{"k":0,"ix":3},"m":1,"ix":2,"nm":"Trim Paths 1","mn":"ADBE Vector Filter - Trim"},{"ty":"st","fillEnabled":true,"c":{"k":[1,1,1,1]},"o":{"k":100},"w":{"k":2},"lc":1,"lj":1,"ml":4,"nm":"Stroke 1","mn":"ADBE Vector Graphic - Stroke"}],"ip":25,"op":60,"st":0,"bm":0,"sr":1},{"ddd":0,"ind":3,"ty":4,"nm":"20","ks":{"o":{"k":100},"r":{"k":0},"p":{"k":[168.625,234.157,0]},"a":{"k":[0,0,0]},"s":{"k":[{"i":{"x":[0.667,0.667,0.667],"y":[1,1,0.667]},"o":{"x":[0.333,0.333,0.333],"y":[0,0,0.333]},"n":["0p667_1_0p333_0","0p667_1_0p333_0","0p667_0p667_0p333_0p333"],"t":19.946,"s":[0,0,100],"e":[100,100,100]},{"t":24}]}},"ao":0,"shapes":[{"d":1,"ty":"el","s":{"k":[16,16]},"p":{"k":[0,0]},"nm":"Ellipse Path 1","mn":"ADBE Vector Shape - Ellipse"},{"ty":"fl","fillEnabled":true,"c":{"k":[1,1,1,1]},"o":{"k":100},"nm":"Fill 1","mn":"ADBE Vector Graphic - Fill"}],"ip":0,"op":60,"st":-1,"bm":0,"sr":1},{"ddd":0,"ind":4,"ty":4,"nm":"19","ks":{"o":{"k":100},"r":{"k":0},"p":{"k":[101.125,234.157,0]},"a":{"k":[0,0,0]},"s":{"k":[{"i":{"x":[0.667,0.667,0.667],"y":[1,1,0.667]},"o":{"x":[0.333,0.333,0.333],"y":[0,0,0.333]},"n":["0p667_1_0p333_0","0p667_1_0p333_0","0p667_0p667_0p333_0p333"],"t":20.946,"s":[0,0,100],"e":[100,100,100]},{"t":25}]}},"ao":0,"shapes":[{"d":1,"ty":"el","s":{"k":[16,16]},"p":{"k":[0,0]},"nm":"Ellipse Path 1","mn":"ADBE Vector Shape - Ellipse"},{"ty":"fl","fillEnabled":true,"c":{"k":[1,1,1,1]},"o":{"k":100},"nm":"Fill 1","mn":"ADBE Vector Graphic - Fill"}],"ip":0,"op":60,"st":0,"bm":0,"sr":1},{"ddd":0,"ind":5,"ty":4,"nm":"4 line 4","ks":{"o":{"k":100},"r":{"k":55},"p":{"k":[204.25,189.792,0]},"a":{"k":[11.653,-283.014,0]},"s":{"k":[100,100,100]}},"ao":0,"shapes":[{"ty":"gr","it":[{"ind":0,"ty":"sh","ks":{"k":{"i":[[0,0],[0,0]],"o":[[0,0],[0,0]],"v":[[25.4,-291.548],[-2.093,-274.48]],"c":false}},"nm":"Path 1","mn":"ADBE Vector Shape - Group"},{"ty":"tm","s":{"k":[{"i":{"x":[0.667],"y":[1]},"o":{"x":[0.333],"y":[0]},"n":["0p667_1_0p333_0"],"t":17.568,"s":[100],"e":[0]},{"t":21.6220703125}],"ix":1},"e":{"k":100,"ix":2},"o":{"k":0,"ix":3},"m":1,"ix":2,"nm":"Trim Paths 1","mn":"ADBE Vector Filter - Trim"},{"ty":"st","fillEnabled":true,"c":{"k":[1,1,1,1]},"o":{"k":100},"w":{"k":2},"lc":1,"lj":1,"ml":4,"nm":"Stroke 1","mn":"ADBE Vector Graphic - Stroke"},{"ty":"fl","fillEnabled":true,"c":{"k":[1,1,1,1]},"o":{"k":100},"nm":"Fill 1","mn":"ADBE Vector Graphic - Fill"},{"ty":"tr","p":{"k":[-7.25,-374.5],"ix":2},"a":{"k":[-7.25,-374.5],"ix":1},"s":{"k":[100,100],"ix":3},"r":{"k":0,"ix":6},"o":{"k":100,"ix":7},"sk":{"k":0,"ix":4},"sa":{"k":0,"ix":5},"nm":"Transform"}],"nm":"Shape 1","np":4,"mn":"ADBE Vector Group"},{"ind":1,"ty":"sh","ks":{"k":{"i":[[0,0],[0,0]],"o":[[0,0],[0,0]],"v":[[0,0],[0,0]],"c":false}},"nm":"Path 1","mn":"ADBE Vector Shape - Group"},{"ty":"st","fillEnabled":true,"c":{"k":[1,1,1,1]},"o":{"k":100},"w":{"k":2},"lc":1,"lj":1,"ml":4,"nm":"Stroke 1","mn":"ADBE Vector Graphic - Stroke"}],"ip":0,"op":60,"st":0,"bm":0,"sr":1},{"ddd":0,"ind":6,"ty":4,"nm":"4 line 3","ks":{"o":{"k":100},"r":{"k":55},"p":{"k":[161.125,186.542,0]},"a":{"k":[-15.744,-249.552,0]},"s":{"k":[100,100,100]}},"ao":0,"shapes":[{"ty":"gr","it":[{"ind":0,"ty":"sh","ks":{"k":{"i":[[0,0],[0,0]],"o":[[0,0],[0,0]],"v":[[-29.396,-224.624],[-2.093,-274.48]],"c":false}},"nm":"Path 1","mn":"ADBE Vector Shape - Group"},{"ty":"tm","s":{"k":[{"i":{"x":[0.667],"y":[1]},"o":{"x":[0.333],"y":[0]},"n":["0p667_1_0p333_0"],"t":17.568,"s":[100],"e":[0]},{"t":21.6220703125}],"ix":1},"e":{"k":100,"ix":2},"o":{"k":0,"ix":3},"m":1,"ix":2,"nm":"Trim Paths 1","mn":"ADBE Vector Filter - Trim"},{"ty":"st","fillEnabled":true,"c":{"k":[1,1,1,1]},"o":{"k":100},"w":{"k":2},"lc":1,"lj":1,"ml":4,"nm":"Stroke 1","mn":"ADBE Vector Graphic - Stroke"},{"ty":"fl","fillEnabled":true,"c":{"k":[1,1,1,1]},"o":{"k":100},"nm":"Fill 1","mn":"ADBE Vector Graphic - Fill"},{"ty":"tr","p":{"k":[-7.25,-374.5],"ix":2},"a":{"k":[-7.25,-374.5],"ix":1},"s":{"k":[100,100],"ix":3},"r":{"k":0,"ix":6},"o":{"k":100,"ix":7},"sk":{"k":0,"ix":4},"sa":{"k":0,"ix":5},"nm":"Transform"}],"nm":"Shape 1","np":4,"mn":"ADBE Vector Group"},{"ind":1,"ty":"sh","ks":{"k":{"i":[[0,0],[0,0]],"o":[[0,0],[0,0]],"v":[[0,0],[0,0]],"c":false}},"nm":"Path 1","mn":"ADBE Vector Shape - Group"},{"ty":"st","fillEnabled":true,"c":{"k":[1,1,1,1]},"o":{"k":100},"w":{"k":2},"lc":1,"lj":1,"ml":4,"nm":"Stroke 1","mn":"ADBE Vector Graphic - Stroke"}],"ip":0,"op":60,"st":0,"bm":0,"sr":1},{"ddd":0,"ind":7,"ty":4,"nm":"4 line 2","ks":{"o":{"k":100},"r":{"k":55},"p":{"k":[181,209.917,0]},"a":{"k":[14.803,-252.425,0]},"s":{"k":[100,100,100]}},"ao":0,"shapes":[{"ty":"gr","it":[{"ind":0,"ty":"sh","ks":{"k":{"i":[[0,0],[0,0]],"o":[[0,0],[0,0]],"v":[[28.401,-225.661],[-2.093,-274.48]],"c":false}},"nm":"Path 1","mn":"ADBE Vector Shape - Group"},{"ty":"tm","s":{"k":[{"i":{"x":[0.667],"y":[1]},"o":{"x":[0.333],"y":[0]},"n":["0p667_1_0p333_0"],"t":17.568,"s":[100],"e":[0]},{"t":21.6220703125}],"ix":1},"e":{"k":100,"ix":2},"o":{"k":0,"ix":3},"m":1,"ix":2,"nm":"Trim Paths 1","mn":"ADBE Vector Filter - Trim"},{"ty":"st","fillEnabled":true,"c":{"k":[1,1,1,1]},"o":{"k":100},"w":{"k":2},"lc":1,"lj":1,"ml":4,"nm":"Stroke 1","mn":"ADBE Vector Graphic - Stroke"},{"ty":"fl","fillEnabled":true,"c":{"k":[1,1,1,1]},"o":{"k":100},"nm":"Fill 1","mn":"ADBE Vector Graphic - Fill"},{"ty":"tr","p":{"k":[-7.25,-374.5],"ix":2},"a":{"k":[-7.25,-374.5],"ix":1},"s":{"k":[100,100],"ix":3},"r":{"k":0,"ix":6},"o":{"k":100,"ix":7},"sk":{"k":0,"ix":4},"sa":{"k":0,"ix":5},"nm":"Transform"}],"nm":"Shape 1","np":4,"mn":"ADBE Vector Group"},{"ind":1,"ty":"sh","ks":{"k":{"i":[[0,0],[0,0]],"o":[[0,0],[0,0]],"v":[[0,0],[0,0]],"c":false}},"nm":"Path 1","mn":"ADBE Vector Shape - Group"},{"ty":"st","fillEnabled":true,"c":{"k":[1,1,1,1]},"o":{"k":100},"w":{"k":2},"lc":1,"lj":1,"ml":4,"nm":"Stroke 1","mn":"ADBE Vector Graphic - Stroke"}],"ip":0,"op":60,"st":0,"bm":0,"sr":1},{"ddd":0,"ind":8,"ty":4,"nm":"4 line 6","ks":{"o":{"k":100},"r":{"k":55},"p":{"k":[92.75,191.449,0]},"a":{"k":[13.011,-282.064,0]},"s":{"k":[100,100,100]}},"ao":0,"shapes":[{"ty":"gr","it":[{"ind":0,"ty":"sh","ks":{"k":{"i":[[0,0],[0,0]],"o":[[0,0],[0,0]],"v":[[35.849,-317.803],[-2.093,-274.48]],"c":false}},"nm":"Path 1","mn":"ADBE Vector Shape - Group"},{"ind":1,"ty":"sh","ks":{"k":{"i":[[0,0],[0,0]],"o":[[0,0],[0,0]],"v":[[-7.028,-244.365],[-2.093,-274.48]],"c":false}},"nm":"Path 2","mn":"ADBE Vector Shape - Group"},{"ty":"tm","s":{"k":[{"i":{"x":[0.667],"y":[1]},"o":{"x":[0.333],"y":[0]},"n":["0p667_1_0p333_0"],"t":17.568,"s":[100],"e":[0]},{"t":21.6220703125}],"ix":1},"e":{"k":100,"ix":2},"o":{"k":0,"ix":3},"m":1,"ix":3,"nm":"Trim Paths 1","mn":"ADBE Vector Filter - Trim"},{"ty":"st","fillEnabled":true,"c":{"k":[1,1,1,1]},"o":{"k":100},"w":{"k":2},"lc":1,"lj":1,"ml":4,"nm":"Stroke 1","mn":"ADBE Vector Graphic - Stroke"},{"ty":"fl","fillEnabled":true,"c":{"k":[1,1,1,1]},"o":{"k":100},"nm":"Fill 1","mn":"ADBE Vector Graphic - Fill"},{"ty":"tr","p":{"k":[-7.25,-374.5],"ix":2},"a":{"k":[-7.25,-374.5],"ix":1},"s":{"k":[100,100],"ix":3},"r":{"k":0,"ix":6},"o":{"k":100,"ix":7},"sk":{"k":0,"ix":4},"sa":{"k":0,"ix":5},"nm":"Transform"}],"nm":"Shape 1","np":5,"mn":"ADBE Vector Group"},{"ind":1,"ty":"sh","ks":{"k":{"i":[[0,0],[0,0]],"o":[[0,0],[0,0]],"v":[[0,0],[0,0]],"c":false}},"nm":"Path 1","mn":"ADBE Vector Shape - Group"},{"ty":"st","fillEnabled":true,"c":{"k":[1,1,1,1]},"o":{"k":100},"w":{"k":2},"lc":1,"lj":1,"ml":4,"nm":"Stroke 1","mn":"ADBE Vector Graphic - Stroke"}],"ip":0,"op":60,"st":0,"bm":0,"sr":1},{"ddd":0,"ind":9,"ty":4,"nm":"4 line 5","ks":{"o":{"k":100},"r":{"k":55},"p":{"k":[64.125,190.5,0]},"a":{"k":[-4.185,-259.159,0]},"s":{"k":[100,100,100]}},"ao":0,"shapes":[{"ty":"gr","it":[{"ind":0,"ty":"sh","ks":{"k":{"i":[[0,0],[0,0]],"o":[[0,0],[0,0]],"v":[[-7.028,-244.365],[-2.093,-274.48]],"c":false}},"nm":"Path 1","mn":"ADBE Vector Shape - Group"},{"ind":1,"ty":"sh","ks":{"k":{"i":[[0,0],[0,0]],"o":[[0,0],[0,0]],"v":[[-7.028,-244.365],[-2.093,-274.48]],"c":false}},"nm":"Path 2","mn":"ADBE Vector Shape - Group"},{"ty":"tm","s":{"k":[{"i":{"x":[0.667],"y":[1]},"o":{"x":[0.333],"y":[0]},"n":["0p667_1_0p333_0"],"t":17.568,"s":[100],"e":[0]},{"t":21.6220703125}],"ix":1},"e":{"k":100,"ix":2},"o":{"k":0,"ix":3},"m":1,"ix":3,"nm":"Trim Paths 1","mn":"ADBE Vector Filter - Trim"},{"ty":"st","fillEnabled":true,"c":{"k":[1,1,1,1]},"o":{"k":100},"w":{"k":2},"lc":1,"lj":1,"ml":4,"nm":"Stroke 1","mn":"ADBE Vector Graphic - Stroke"},{"ty":"fl","fillEnabled":true,"c":{"k":[1,1,1,1]},"o":{"k":100},"nm":"Fill 1","mn":"ADBE Vector Graphic - Fill"},{"ty":"tr","p":{"k":[-7.25,-374.5],"ix":2},"a":{"k":[-7.25,-374.5],"ix":1},"s":{"k":[100,100],"ix":3},"r":{"k":0,"ix":6},"o":{"k":100,"ix":7},"sk":{"k":0,"ix":4},"sa":{"k":0,"ix":5},"nm":"Transform"}],"nm":"Shape 1","np":5,"mn":"ADBE Vector Group"},{"ind":1,"ty":"sh","ks":{"k":{"i":[[0,0],[0,0]],"o":[[0,0],[0,0]],"v":[[0,0],[0,0]],"c":false}},"nm":"Path 1","mn":"ADBE Vector Shape - Group"},{"ty":"st","fillEnabled":true,"c":{"k":[1,1,1,1]},"o":{"k":100},"w":{"k":2},"lc":1,"lj":1,"ml":4,"nm":"Stroke 1","mn":"ADBE Vector Graphic - Stroke"}],"ip":0,"op":60,"st":0,"bm":0,"sr":1},{"ddd":0,"ind":10,"ty":4,"nm":"4 line 8","ks":{"o":{"k":100},"r":{"k":55},"p":{"k":[151.799,213.47,0]},"a":{"k":[64.919,-317.803,0]},"s":{"k":[100,100,100]}},"ao":0,"shapes":[{"ty":"gr","it":[{"ind":0,"ty":"sh","ks":{"k":{"i":[[0,0],[0,0]],"o":[[0,0],[0,0]],"v":[[94.322,-321.112],[35.515,-314.678]],"c":false}},"nm":"Path 1","mn":"ADBE Vector Shape - Group"},{"ty":"tm","s":{"k":[{"i":{"x":[0.667],"y":[1]},"o":{"x":[0.333],"y":[0]},"n":["0p667_1_0p333_0"],"t":17.568,"s":[100],"e":[0]},{"t":21.6220703125}],"ix":1},"e":{"k":100,"ix":2},"o":{"k":0,"ix":3},"m":1,"ix":2,"nm":"Trim Paths 1","mn":"ADBE Vector Filter - Trim"},{"ty":"st","fillEnabled":true,"c":{"k":[1,1,1,1]},"o":{"k":100},"w":{"k":2},"lc":1,"lj":1,"ml":4,"nm":"Stroke 1","mn":"ADBE Vector Graphic - Stroke"},{"ty":"fl","fillEnabled":true,"c":{"k":[1,1,1,1]},"o":{"k":100},"nm":"Fill 1","mn":"ADBE Vector Graphic - Fill"},{"ty":"tr","p":{"k":[-7.25,-374.5],"ix":2},"a":{"k":[-7.25,-374.5],"ix":1},"s":{"k":[100,100],"ix":3},"r":{"k":0,"ix":6},"o":{"k":100,"ix":7},"sk":{"k":0,"ix":4},"sa":{"k":0,"ix":5},"nm":"Transform"}],"nm":"Shape 1","np":4,"mn":"ADBE Vector Group"},{"ind":1,"ty":"sh","ks":{"k":{"i":[[0,0],[0,0]],"o":[[0,0],[0,0]],"v":[[0,0],[0,0]],"c":false}},"nm":"Path 1","mn":"ADBE Vector Shape - Group"},{"ty":"st","fillEnabled":true,"c":{"k":[1,1,1,1]},"o":{"k":100},"w":{"k":2},"lc":1,"lj":1,"ml":4,"nm":"Stroke 1","mn":"ADBE Vector Graphic - Stroke"}],"ip":0,"op":60,"st":0,"bm":0,"sr":1},{"ddd":0,"ind":11,"ty":4,"nm":"4 line 7","ks":{"o":{"k":100},"r":{"k":55},"p":{"k":[116.5,214.292,0]},"a":{"k":[45.345,-288.416,0]},"s":{"k":[100,100,100]}},"ao":0,"shapes":[{"ty":"gr","it":[{"ind":0,"ty":"sh","ks":{"k":{"i":[[0,0],[0,0]],"o":[[0,0],[0,0]],"v":[[55.175,-262.154],[35.515,-314.678]],"c":false}},"nm":"Path 1","mn":"ADBE Vector Shape - Group"},{"ty":"tm","s":{"k":[{"i":{"x":[0.667],"y":[1]},"o":{"x":[0.333],"y":[0]},"n":["0p667_1_0p333_0"],"t":17.568,"s":[100],"e":[0]},{"t":21.6220703125}],"ix":1},"e":{"k":100,"ix":2},"o":{"k":0,"ix":3},"m":1,"ix":2,"nm":"Trim Paths 1","mn":"ADBE Vector Filter - Trim"},{"ty":"st","fillEnabled":true,"c":{"k":[1,1,1,1]},"o":{"k":100},"w":{"k":2},"lc":1,"lj":1,"ml":4,"nm":"Stroke 1","mn":"ADBE Vector Graphic - Stroke"},{"ty":"fl","fillEnabled":true,"c":{"k":[1,1,1,1]},"o":{"k":100},"nm":"Fill 1","mn":"ADBE Vector Graphic - Fill"},{"ty":"tr","p":{"k":[-7.25,-374.5],"ix":2},"a":{"k":[-7.25,-374.5],"ix":1},"s":{"k":[100,100],"ix":3},"r":{"k":0,"ix":6},"o":{"k":100,"ix":7},"sk":{"k":0,"ix":4},"sa":{"k":0,"ix":5},"nm":"Transform"}],"nm":"Shape 1","np":4,"mn":"ADBE Vector Group"},{"ind":1,"ty":"sh","ks":{"k":{"i":[[0,0],[0,0]],"o":[[0,0],[0,0]],"v":[[0,0],[0,0]],"c":false}},"nm":"Path 1","mn":"ADBE Vector Shape - Group"},{"ty":"st","fillEnabled":true,"c":{"k":[1,1,1,1]},"o":{"k":100},"w":{"k":2},"lc":1,"lj":1,"ml":4,"nm":"Stroke 1","mn":"ADBE Vector Graphic - Stroke"}],"ip":0,"op":60,"st":0,"bm":0,"sr":1},{"ddd":0,"ind":12,"ty":4,"nm":"4 line","ks":{"o":{"k":100},"r":{"k":55},"p":{"k":[92.508,209.661,0]},"a":{"k":[27.79,-271.419,0]},"s":{"k":[100,100,100]}},"ao":0,"shapes":[{"ty":"gr","it":[{"ind":0,"ty":"sh","ks":{"k":{"i":[[0,0],[0,0]],"o":[[0,0],[0,0]],"v":[[57.674,-265.287],[-2.093,-274.48]],"c":false}},"nm":"Path 1","mn":"ADBE Vector Shape - Group"},{"ty":"tm","s":{"k":[{"i":{"x":[0.667],"y":[1]},"o":{"x":[0.333],"y":[0]},"n":["0p667_1_0p333_0"],"t":17.568,"s":[100],"e":[0]},{"t":21.6220703125}],"ix":1},"e":{"k":100,"ix":2},"o":{"k":0,"ix":3},"m":1,"ix":2,"nm":"Trim Paths 1","mn":"ADBE Vector Filter - Trim"},{"ty":"st","fillEnabled":true,"c":{"k":[1,1,1,1]},"o":{"k":100},"w":{"k":2},"lc":1,"lj":1,"ml":4,"nm":"Stroke 1","mn":"ADBE Vector Graphic - Stroke"},{"ty":"fl","fillEnabled":true,"c":{"k":[1,1,1,1]},"o":{"k":100},"nm":"Fill 1","mn":"ADBE Vector Graphic - Fill"},{"ty":"tr","p":{"k":[-7.25,-374.5],"ix":2},"a":{"k":[-7.25,-374.5],"ix":1},"s":{"k":[100,100],"ix":3},"r":{"k":0,"ix":6},"o":{"k":100,"ix":7},"sk":{"k":0,"ix":4},"sa":{"k":0,"ix":5},"nm":"Transform"}],"nm":"Shape 1","np":4,"mn":"ADBE Vector Group"},{"ind":1,"ty":"sh","ks":{"k":{"i":[[0,0],[0,0]],"o":[[0,0],[0,0]],"v":[[0,0],[0,0]],"c":false}},"nm":"Path 1","mn":"ADBE Vector Shape - Group"},{"ty":"st","fillEnabled":true,"c":{"k":[1,1,1,1]},"o":{"k":100},"w":{"k":2},"lc":1,"lj":1,"ml":4,"nm":"Stroke 1","mn":"ADBE Vector Graphic - Stroke"}],"ip":0,"op":60,"st":0,"bm":0,"sr":1},{"ddd":0,"ind":13,"ty":4,"nm":"18","ks":{"o":{"k":100},"r":{"k":0},"p":{"k":[49.75,197.375,0]},"a":{"k":[0,0,0]},"s":{"k":[{"i":{"x":[0.667,0.667,0.667],"y":[1,1,0.667]},"o":{"x":[0.333,0.333,0.333],"y":[0,0,0.333]},"n":["0p667_1_0p333_0","0p667_1_0p333_0","0p667_0p667_0p333_0p333"],"t":18.919,"s":[0,0,100],"e":[100,100,100]},{"t":22.97265625}]}},"ao":0,"shapes":[{"d":1,"ty":"el","s":{"k":[16,16]},"p":{"k":[0,0]},"nm":"Ellipse Path 1","mn":"ADBE Vector Shape - Ellipse"},{"ty":"fl","fillEnabled":true,"c":{"k":[1,1,1,1]},"o":{"k":100},"nm":"Fill 1","mn":"ADBE Vector Graphic - Fill"}],"ip":0,"op":60,"st":0,"bm":0,"sr":1},{"ddd":0,"ind":14,"ty":4,"nm":"17","ks":{"o":{"k":100},"r":{"k":0},"p":{"k":[218.25,197.375,0]},"a":{"k":[0,0,0]},"s":{"k":[{"i":{"x":[0.667,0.667,0.667],"y":[1,1,0.667]},"o":{"x":[0.333,0.333,0.333],"y":[0,0,0.333]},"n":["0p667_1_0p333_0","0p667_1_0p333_0","0p667_0p667_0p333_0p333"],"t":18.919,"s":[0,0,100],"e":[100,100,100]},{"t":22.97265625}]}},"ao":0,"shapes":[{"d":1,"ty":"el","s":{"k":[16,16]},"p":{"k":[0,0]},"nm":"Ellipse Path 1","mn":"ADBE Vector Shape - Ellipse"},{"ty":"fl","fillEnabled":true,"c":{"k":[1,1,1,1]},"o":{"k":100},"nm":"Fill 1","mn":"ADBE Vector Graphic - Fill"}],"ip":0,"op":60,"st":0,"bm":0,"sr":1},{"ddd":0,"ind":15,"ty":4,"nm":"16","ks":{"o":{"k":100},"r":{"k":0},"p":{"k":[239.75,135,0]},"a":{"k":[0,0,0]},"s":{"k":[{"i":{"x":[0.667,0.667,0.667],"y":[1,1,0.667]},"o":{"x":[0.333,0.333,0.333],"y":[0,0,0.333]},"n":["0p667_1_0p333_0","0p667_1_0p333_0","0p667_0p667_0p333_0p333"],"t":18.919,"s":[0,0,100],"e":[100,100,100]},{"t":22.97265625}]}},"ao":0,"shapes":[{"d":1,"ty":"el","s":{"k":[16,16]},"p":{"k":[0,0]},"nm":"Ellipse Path 1","mn":"ADBE Vector Shape - Ellipse"},{"ty":"fl","fillEnabled":true,"c":{"k":[1,1,1,1]},"o":{"k":100},"nm":"Fill 1","mn":"ADBE Vector Graphic - Fill"}],"ip":0,"op":60,"st":0,"bm":0,"sr":1},{"ddd":0,"ind":16,"ty":4,"nm":"15","ks":{"o":{"k":100},"r":{"k":0},"p":{"k":[30,135,0]},"a":{"k":[0,0,0]},"s":{"k":[{"i":{"x":[0.667,0.667,0.667],"y":[1,1,0.667]},"o":{"x":[0.333,0.333,0.333],"y":[0,0,0.333]},"n":["0p667_1_0p333_0","0p667_1_0p333_0","0p667_0p667_0p333_0p333"],"t":18.919,"s":[0,0,100],"e":[100,100,100]},{"t":22.97265625}]}},"ao":0,"shapes":[{"d":1,"ty":"el","s":{"k":[16,16]},"p":{"k":[0,0]},"nm":"Ellipse Path 1","mn":"ADBE Vector Shape - Ellipse"},{"ty":"fl","fillEnabled":true,"c":{"k":[1,1,1,1]},"o":{"k":100},"nm":"Fill 1","mn":"ADBE Vector Graphic - Fill"}],"ip":0,"op":60,"st":0,"bm":0,"sr":1},{"ddd":0,"ind":17,"ty":4,"nm":"2 line 11","ks":{"o":{"k":100},"r":{"k":55},"p":{"k":[217.125,168.167,0]},"a":{"k":[30.898,-307.23,0]},"s":{"k":[100,100,100]}},"ao":0,"shapes":[{"ty":"gr","it":[{"ind":0,"ty":"sh","ks":{"k":{"i":[[0,0],[0,0]],"o":[[0,0],[0,0]],"v":[[18.485,-347.052],[0.986,-324.207]],"c":false}},"nm":"Path 1","mn":"ADBE Vector Shape - Group"},{"ty":"tm","s":{"k":[{"i":{"x":[0.667],"y":[1]},"o":{"x":[0.333],"y":[0]},"n":["0p667_1_0p333_0"],"t":15.541,"s":[100],"e":[0]},{"t":19.5947265625}],"ix":1},"e":{"k":100,"ix":2},"o":{"k":0,"ix":3},"m":1,"ix":2,"nm":"Trim Paths 1","mn":"ADBE Vector Filter - Trim"},{"ty":"st","fillEnabled":true,"c":{"k":[1,1,1,1]},"o":{"k":100},"w":{"k":2},"lc":1,"lj":1,"ml":4,"nm":"Stroke 1","mn":"ADBE Vector Graphic - Stroke"},{"ty":"fl","fillEnabled":true,"c":{"k":[1,1,1,1]},"o":{"k":100},"nm":"Fill 1","mn":"ADBE Vector Graphic - Fill"},{"ty":"tr","p":{"k":[-7.25,-374.5],"ix":2},"a":{"k":[-7.25,-374.5],"ix":1},"s":{"k":[100,100],"ix":3},"r":{"k":0,"ix":6},"o":{"k":100,"ix":7},"sk":{"k":0,"ix":4},"sa":{"k":0,"ix":5},"nm":"Transform"}],"nm":"Shape 1","np":4,"mn":"ADBE Vector Group"},{"ind":1,"ty":"sh","ks":{"k":{"i":[[0,0],[0,0]],"o":[[0,0],[0,0]],"v":[[0,0],[0,0]],"c":false}},"nm":"Path 1","mn":"ADBE Vector Shape - Group"},{"ty":"st","fillEnabled":true,"c":{"k":[1,1,1,1]},"o":{"k":100},"w":{"k":2},"lc":1,"lj":1,"ml":4,"nm":"Stroke 1","mn":"ADBE Vector Graphic - Stroke"}],"ip":0,"op":60,"st":0,"bm":0,"sr":1},{"ddd":0,"ind":18,"ty":4,"nm":"2 line 17","ks":{"o":{"k":100},"r":{"k":55},"p":{"k":[226.625,157.542,0]},"a":{"k":[27.644,-321.106,0]},"s":{"k":[100,100,100]}},"ao":0,"shapes":[{"ty":"gr","it":[{"ind":0,"ty":"sh","ks":{"k":{"i":[[0,0],[0,0]],"o":[[0,0],[0,0]],"v":[[28.04,-276.576],[0.986,-324.207]],"c":false}},"nm":"Path 1","mn":"ADBE Vector Shape - Group"},{"ty":"tm","s":{"k":[{"i":{"x":[0.667],"y":[1]},"o":{"x":[0.333],"y":[0]},"n":["0p667_1_0p333_0"],"t":15.541,"s":[100],"e":[0]},{"t":19.5947265625}],"ix":1},"e":{"k":100,"ix":2},"o":{"k":0,"ix":3},"m":1,"ix":2,"nm":"Trim Paths 1","mn":"ADBE Vector Filter - Trim"},{"ty":"st","fillEnabled":true,"c":{"k":[1,1,1,1]},"o":{"k":100},"w":{"k":2},"lc":1,"lj":1,"ml":4,"nm":"Stroke 1","mn":"ADBE Vector Graphic - Stroke"},{"ty":"fl","fillEnabled":true,"c":{"k":[1,1,1,1]},"o":{"k":100},"nm":"Fill 1","mn":"ADBE Vector Graphic - Fill"},{"ty":"tr","p":{"k":[-7.25,-374.5],"ix":2},"a":{"k":[-7.25,-374.5],"ix":1},"s":{"k":[100,100],"ix":3},"r":{"k":0,"ix":6},"o":{"k":100,"ix":7},"sk":{"k":0,"ix":4},"sa":{"k":0,"ix":5},"nm":"Transform"}],"nm":"Shape 1","np":4,"mn":"ADBE Vector Group"},{"ind":1,"ty":"sh","ks":{"k":{"i":[[0,0],[0,0]],"o":[[0,0],[0,0]],"v":[[0,0],[0,0]],"c":false}},"nm":"Path 1","mn":"ADBE Vector Shape - Group"},{"ty":"st","fillEnabled":true,"c":{"k":[1,1,1,1]},"o":{"k":100},"w":{"k":2},"lc":1,"lj":1,"ml":4,"nm":"Stroke 1","mn":"ADBE Vector Graphic - Stroke"}],"ip":0,"op":60,"st":0,"bm":0,"sr":1},{"ddd":0,"ind":19,"ty":4,"nm":"2 line 10","ks":{"o":{"k":100},"r":{"k":55},"p":{"k":[226.625,157.542,0]},"a":{"k":[27.644,-321.106,0]},"s":{"k":[100,100,100]}},"ao":0,"shapes":[{"ty":"gr","it":[{"ind":0,"ty":"sh","ks":{"k":{"i":[[0,0],[0,0]],"o":[[0,0],[0,0]],"v":[[60.811,-290.253],[0.986,-324.207]],"c":false}},"nm":"Path 1","mn":"ADBE Vector Shape - Group"},{"ty":"tm","s":{"k":[{"i":{"x":[0.667],"y":[1]},"o":{"x":[0.333],"y":[0]},"n":["0p667_1_0p333_0"],"t":15.541,"s":[100],"e":[0]},{"t":19.5947265625}],"ix":1},"e":{"k":100,"ix":2},"o":{"k":0,"ix":3},"m":1,"ix":2,"nm":"Trim Paths 1","mn":"ADBE Vector Filter - Trim"},{"ty":"st","fillEnabled":true,"c":{"k":[1,1,1,1]},"o":{"k":100},"w":{"k":2},"lc":1,"lj":1,"ml":4,"nm":"Stroke 1","mn":"ADBE Vector Graphic - Stroke"},{"ty":"fl","fillEnabled":true,"c":{"k":[1,1,1,1]},"o":{"k":100},"nm":"Fill 1","mn":"ADBE Vector Graphic - Fill"},{"ty":"tr","p":{"k":[-7.25,-374.5],"ix":2},"a":{"k":[-7.25,-374.5],"ix":1},"s":{"k":[100,100],"ix":3},"r":{"k":0,"ix":6},"o":{"k":100,"ix":7},"sk":{"k":0,"ix":4},"sa":{"k":0,"ix":5},"nm":"Transform"}],"nm":"Shape 1","np":4,"mn":"ADBE Vector Group"},{"ind":1,"ty":"sh","ks":{"k":{"i":[[0,0],[0,0]],"o":[[0,0],[0,0]],"v":[[0,0],[0,0]],"c":false}},"nm":"Path 1","mn":"ADBE Vector Shape - Group"},{"ty":"st","fillEnabled":true,"c":{"k":[1,1,1,1]},"o":{"k":100},"w":{"k":2},"lc":1,"lj":1,"ml":4,"nm":"Stroke 1","mn":"ADBE Vector Graphic - Stroke"}],"ip":0,"op":60,"st":0,"bm":0,"sr":1},{"ddd":0,"ind":20,"ty":4,"nm":"2 line 15","ks":{"o":{"k":100},"r":{"k":55},"p":{"k":[51.625,167.167,0]},"a":{"k":[26.925,-303.298,0]},"s":{"k":[100,100,100]}},"ao":0,"shapes":[{"ty":"gr","it":[{"ind":0,"ty":"sh","ks":{"k":{"i":[[0,0],[0,0]],"o":[[0,0],[0,0]],"v":[[29.957,-363.435],[0.986,-324.207]],"c":false}},"nm":"Path 1","mn":"ADBE Vector Shape - Group"},{"ind":1,"ty":"sh","ks":{"k":{"i":[[0,0],[0,0]],"o":[[0,0],[0,0]],"v":[[47.957,-492.441],[93.925,-454.759]],"c":false}},"nm":"Path 2","mn":"ADBE Vector Shape - Group"},{"ty":"tm","s":{"k":[{"i":{"x":[0.667],"y":[1]},"o":{"x":[0.333],"y":[0]},"n":["0p667_1_0p333_0"],"t":15.541,"s":[100],"e":[0]},{"t":19.5947265625}],"ix":1},"e":{"k":100,"ix":2},"o":{"k":0,"ix":3},"m":1,"ix":3,"nm":"Trim Paths 1","mn":"ADBE Vector Filter - Trim"},{"ty":"st","fillEnabled":true,"c":{"k":[1,1,1,1]},"o":{"k":100},"w":{"k":2},"lc":1,"lj":1,"ml":4,"nm":"Stroke 1","mn":"ADBE Vector Graphic - Stroke"},{"ty":"fl","fillEnabled":true,"c":{"k":[1,1,1,1]},"o":{"k":100},"nm":"Fill 1","mn":"ADBE Vector Graphic - Fill"},{"ty":"tr","p":{"k":[-7.25,-374.5],"ix":2},"a":{"k":[-7.25,-374.5],"ix":1},"s":{"k":[100,100],"ix":3},"r":{"k":0,"ix":6},"o":{"k":100,"ix":7},"sk":{"k":0,"ix":4},"sa":{"k":0,"ix":5},"nm":"Transform"}],"nm":"Shape 1","np":5,"mn":"ADBE Vector Group"},{"ind":1,"ty":"sh","ks":{"k":{"i":[[0,0],[0,0]],"o":[[0,0],[0,0]],"v":[[0,0],[0,0]],"c":false}},"nm":"Path 1","mn":"ADBE Vector Shape - Group"},{"ty":"st","fillEnabled":true,"c":{"k":[1,1,1,1]},"o":{"k":100},"w":{"k":2},"lc":1,"lj":1,"ml":4,"nm":"Stroke 1","mn":"ADBE Vector Graphic - Stroke"}],"ip":0,"op":60,"st":0,"bm":0,"sr":1},{"ddd":0,"ind":21,"ty":4,"nm":"2 line 14","ks":{"o":{"k":100},"r":{"k":55},"p":{"k":[51.625,167.167,0]},"a":{"k":[26.925,-303.298,0]},"s":{"k":[100,100,100]}},"ao":0,"shapes":[{"ty":"gr","it":[{"ind":0,"ty":"sh","ks":{"k":{"i":[[0,0],[0,0]],"o":[[0,0],[0,0]],"v":[[29.957,-363.435],[0.986,-324.207]],"c":false}},"nm":"Path 1","mn":"ADBE Vector Shape - Group"},{"ind":1,"ty":"sh","ks":{"k":{"i":[[0,0],[0,0]],"o":[[0,0],[0,0]],"v":[[29.526,-362.821],[93.925,-454.759]],"c":false}},"nm":"Path 2","mn":"ADBE Vector Shape - Group"},{"ty":"tm","s":{"k":[{"i":{"x":[0.667],"y":[1]},"o":{"x":[0.333],"y":[0]},"n":["0p667_1_0p333_0"],"t":15.541,"s":[100],"e":[0]},{"t":19.5947265625}],"ix":1},"e":{"k":100,"ix":2},"o":{"k":0,"ix":3},"m":1,"ix":3,"nm":"Trim Paths 1","mn":"ADBE Vector Filter - Trim"},{"ty":"st","fillEnabled":true,"c":{"k":[1,1,1,1]},"o":{"k":100},"w":{"k":2},"lc":1,"lj":1,"ml":4,"nm":"Stroke 1","mn":"ADBE Vector Graphic - Stroke"},{"ty":"fl","fillEnabled":true,"c":{"k":[1,1,1,1]},"o":{"k":100},"nm":"Fill 1","mn":"ADBE Vector Graphic - Fill"},{"ty":"tr","p":{"k":[-7.25,-374.5],"ix":2},"a":{"k":[-7.25,-374.5],"ix":1},"s":{"k":[100,100],"ix":3},"r":{"k":0,"ix":6},"o":{"k":100,"ix":7},"sk":{"k":0,"ix":4},"sa":{"k":0,"ix":5},"nm":"Transform"}],"nm":"Shape 1","np":5,"mn":"ADBE Vector Group"},{"ind":1,"ty":"sh","ks":{"k":{"i":[[0,0],[0,0]],"o":[[0,0],[0,0]],"v":[[0,0],[0,0]],"c":false}},"nm":"Path 1","mn":"ADBE Vector Shape - Group"},{"ty":"st","fillEnabled":true,"c":{"k":[1,1,1,1]},"o":{"k":100},"w":{"k":2},"lc":1,"lj":1,"ml":4,"nm":"Stroke 1","mn":"ADBE Vector Graphic - Stroke"}],"ip":0,"op":60,"st":0,"bm":0,"sr":1},{"ddd":0,"ind":22,"ty":4,"nm":"2 line 13","ks":{"o":{"k":100},"r":{"k":55},"p":{"k":[51.625,167.167,0]},"a":{"k":[26.925,-303.298,0]},"s":{"k":[100,100,100]}},"ao":0,"shapes":[{"ty":"gr","it":[{"ind":0,"ty":"sh","ks":{"k":{"i":[[0,0],[0,0]],"o":[[0,0],[0,0]],"v":[[-48.199,-354.68],[0.986,-324.207]],"c":false}},"nm":"Path 1","mn":"ADBE Vector Shape - Group"},{"ty":"tm","s":{"k":[{"i":{"x":[0.667],"y":[1]},"o":{"x":[0.333],"y":[0]},"n":["0p667_1_0p333_0"],"t":15.541,"s":[100],"e":[0]},{"t":19.5947265625}],"ix":1},"e":{"k":100,"ix":2},"o":{"k":0,"ix":3},"m":1,"ix":2,"nm":"Trim Paths 1","mn":"ADBE Vector Filter - Trim"},{"ty":"st","fillEnabled":true,"c":{"k":[1,1,1,1]},"o":{"k":100},"w":{"k":2},"lc":1,"lj":1,"ml":4,"nm":"Stroke 1","mn":"ADBE Vector Graphic - Stroke"},{"ty":"fl","fillEnabled":true,"c":{"k":[1,1,1,1]},"o":{"k":100},"nm":"Fill 1","mn":"ADBE Vector Graphic - Fill"},{"ty":"tr","p":{"k":[-7.25,-374.5],"ix":2},"a":{"k":[-7.25,-374.5],"ix":1},"s":{"k":[100,100],"ix":3},"r":{"k":0,"ix":6},"o":{"k":100,"ix":7},"sk":{"k":0,"ix":4},"sa":{"k":0,"ix":5},"nm":"Transform"}],"nm":"Shape 1","np":4,"mn":"ADBE Vector Group"},{"ind":1,"ty":"sh","ks":{"k":{"i":[[0,0],[0,0]],"o":[[0,0],[0,0]],"v":[[0,0],[0,0]],"c":false}},"nm":"Path 1","mn":"ADBE Vector Shape - Group"},{"ty":"st","fillEnabled":true,"c":{"k":[1,1,1,1]},"o":{"k":100},"w":{"k":2},"lc":1,"lj":1,"ml":4,"nm":"Stroke 1","mn":"ADBE Vector Graphic - Stroke"}],"ip":0,"op":60,"st":0,"bm":0,"sr":1},{"ddd":0,"ind":23,"ty":4,"nm":"2 line 12","ks":{"o":{"k":100},"r":{"k":55},"p":{"k":[51.625,167.167,0]},"a":{"k":[26.925,-303.298,0]},"s":{"k":[100,100,100]}},"ao":0,"shapes":[{"ty":"gr","it":[{"ind":0,"ty":"sh","ks":{"k":{"i":[[0,0],[0,0]],"o":[[0,0],[0,0]],"v":[[-11.075,-303.964],[0.986,-324.207]],"c":false}},"nm":"Path 1","mn":"ADBE Vector Shape - Group"},{"ty":"tm","s":{"k":[{"i":{"x":[0.667],"y":[1]},"o":{"x":[0.333],"y":[0]},"n":["0p667_1_0p333_0"],"t":15.541,"s":[100],"e":[0]},{"t":19.5947265625}],"ix":1},"e":{"k":100,"ix":2},"o":{"k":0,"ix":3},"m":1,"ix":2,"nm":"Trim Paths 1","mn":"ADBE Vector Filter - Trim"},{"ty":"st","fillEnabled":true,"c":{"k":[1,1,1,1]},"o":{"k":100},"w":{"k":2},"lc":1,"lj":1,"ml":4,"nm":"Stroke 1","mn":"ADBE Vector Graphic - Stroke"},{"ty":"fl","fillEnabled":true,"c":{"k":[1,1,1,1]},"o":{"k":100},"nm":"Fill 1","mn":"ADBE Vector Graphic - Fill"},{"ty":"tr","p":{"k":[-7.25,-374.5],"ix":2},"a":{"k":[-7.25,-374.5],"ix":1},"s":{"k":[100,100],"ix":3},"r":{"k":0,"ix":6},"o":{"k":100,"ix":7},"sk":{"k":0,"ix":4},"sa":{"k":0,"ix":5},"nm":"Transform"}],"nm":"Shape 1","np":4,"mn":"ADBE Vector Group"},{"ind":1,"ty":"sh","ks":{"k":{"i":[[0,0],[0,0]],"o":[[0,0],[0,0]],"v":[[0,0],[0,0]],"c":false}},"nm":"Path 1","mn":"ADBE Vector Shape - Group"},{"ty":"st","fillEnabled":true,"c":{"k":[1,1,1,1]},"o":{"k":100},"w":{"k":2},"lc":1,"lj":1,"ml":4,"nm":"Stroke 1","mn":"ADBE Vector Graphic - Stroke"}],"ip":0,"op":60,"st":0,"bm":0,"sr":1},{"ddd":0,"ind":24,"ty":4,"nm":"2 line 16","ks":{"o":{"k":100},"r":{"k":55},"p":{"k":[51.625,167.167,0]},"a":{"k":[26.925,-303.298,0]},"s":{"k":[100,100,100]}},"ao":0,"shapes":[{"ty":"gr","it":[{"ind":0,"ty":"sh","ks":{"k":{"i":[[0,0],[0,0]],"o":[[0,0],[0,0]],"v":[[54.301,-314.954],[0.986,-324.207]],"c":false}},"nm":"Path 1","mn":"ADBE Vector Shape - Group"},{"ty":"tm","s":{"k":[{"i":{"x":[0.667],"y":[1]},"o":{"x":[0.333],"y":[0]},"n":["0p667_1_0p333_0"],"t":15.541,"s":[100],"e":[0]},{"t":19.5947265625}],"ix":1},"e":{"k":100,"ix":2},"o":{"k":0,"ix":3},"m":1,"ix":2,"nm":"Trim Paths 1","mn":"ADBE Vector Filter - Trim"},{"ty":"st","fillEnabled":true,"c":{"k":[1,1,1,1]},"o":{"k":100},"w":{"k":2},"lc":1,"lj":1,"ml":4,"nm":"Stroke 1","mn":"ADBE Vector Graphic - Stroke"},{"ty":"fl","fillEnabled":true,"c":{"k":[1,1,1,1]},"o":{"k":100},"nm":"Fill 1","mn":"ADBE Vector Graphic - Fill"},{"ty":"tr","p":{"k":[-7.25,-374.5],"ix":2},"a":{"k":[-7.25,-374.5],"ix":1},"s":{"k":[100,100],"ix":3},"r":{"k":0,"ix":6},"o":{"k":100,"ix":7},"sk":{"k":0,"ix":4},"sa":{"k":0,"ix":5},"nm":"Transform"}],"nm":"Shape 1","np":4,"mn":"ADBE Vector Group"},{"ind":1,"ty":"sh","ks":{"k":{"i":[[0,0],[0,0]],"o":[[0,0],[0,0]],"v":[[0,0],[0,0]],"c":false}},"nm":"Path 1","mn":"ADBE Vector Shape - Group"},{"ty":"st","fillEnabled":true,"c":{"k":[1,1,1,1]},"o":{"k":100},"w":{"k":2},"lc":1,"lj":1,"ml":4,"nm":"Stroke 1","mn":"ADBE Vector Graphic - Stroke"}],"ip":0,"op":60,"st":0,"bm":0,"sr":1},{"ddd":0,"ind":25,"ty":4,"nm":"2 line 9","ks":{"o":{"k":100},"r":{"k":55},"p":{"k":[51.625,167.167,0]},"a":{"k":[26.925,-303.298,0]},"s":{"k":[100,100,100]}},"ao":0,"shapes":[{"ty":"gr","it":[{"ind":0,"ty":"sh","ks":{"k":{"i":[[0,0],[0,0]],"o":[[0,0],[0,0]],"v":[[52.863,-282.389],[0.986,-324.207]],"c":false}},"nm":"Path 1","mn":"ADBE Vector Shape - Group"},{"ty":"tm","s":{"k":[{"i":{"x":[0.667],"y":[1]},"o":{"x":[0.333],"y":[0]},"n":["0p667_1_0p333_0"],"t":15.541,"s":[100],"e":[0]},{"t":19.5947265625}],"ix":1},"e":{"k":100,"ix":2},"o":{"k":0,"ix":3},"m":1,"ix":2,"nm":"Trim Paths 1","mn":"ADBE Vector Filter - Trim"},{"ty":"st","fillEnabled":true,"c":{"k":[1,1,1,1]},"o":{"k":100},"w":{"k":2},"lc":1,"lj":1,"ml":4,"nm":"Stroke 1","mn":"ADBE Vector Graphic - Stroke"},{"ty":"fl","fillEnabled":true,"c":{"k":[1,1,1,1]},"o":{"k":100},"nm":"Fill 1","mn":"ADBE Vector Graphic - Fill"},{"ty":"tr","p":{"k":[-7.25,-374.5],"ix":2},"a":{"k":[-7.25,-374.5],"ix":1},"s":{"k":[100,100],"ix":3},"r":{"k":0,"ix":6},"o":{"k":100,"ix":7},"sk":{"k":0,"ix":4},"sa":{"k":0,"ix":5},"nm":"Transform"}],"nm":"Shape 1","np":4,"mn":"ADBE Vector Group"},{"ind":1,"ty":"sh","ks":{"k":{"i":[[0,0],[0,0]],"o":[[0,0],[0,0]],"v":[[0,0],[0,0]],"c":false}},"nm":"Path 1","mn":"ADBE Vector Shape - Group"},{"ty":"st","fillEnabled":true,"c":{"k":[1,1,1,1]},"o":{"k":100},"w":{"k":2},"lc":1,"lj":1,"ml":4,"nm":"Stroke 1","mn":"ADBE Vector Graphic - Stroke"}],"ip":0,"op":60,"st":0,"bm":0,"sr":1},{"ddd":0,"ind":26,"ty":4,"nm":"14","ks":{"o":{"k":100},"r":{"k":0},"p":{"k":[133.25,189.5,0]},"a":{"k":[0,0,0]},"s":{"k":[{"i":{"x":[0.667,0.667,0.667],"y":[1,1,0.667]},"o":{"x":[0.333,0.333,0.333],"y":[0,0,0.333]},"n":["0p667_1_0p333_0","0p667_1_0p333_0","0p667_0p667_0p333_0p333"],"t":14.189,"s":[0,0,100],"e":[100,100,100]},{"t":18.2431640625}]}},"ao":0,"shapes":[{"d":1,"ty":"el","s":{"k":[16,16]},"p":{"k":[0,0]},"nm":"Ellipse Path 1","mn":"ADBE Vector Shape - Ellipse"},{"ty":"fl","fillEnabled":true,"c":{"k":[1,1,1,1]},"o":{"k":100},"nm":"Fill 1","mn":"ADBE Vector Graphic - Fill"}],"ip":0,"op":60,"st":0,"bm":0,"sr":1},{"ddd":0,"ind":27,"ty":4,"nm":"13","ks":{"o":{"k":100},"r":{"k":0},"p":{"k":[189,182.5,0]},"a":{"k":[0,0,0]},"s":{"k":[{"i":{"x":[0.667,0.667,0.667],"y":[1,1,0.667]},"o":{"x":[0.333,0.333,0.333],"y":[0,0,0.333]},"n":["0p667_1_0p333_0","0p667_1_0p333_0","0p667_0p667_0p333_0p333"],"t":14.189,"s":[0,0,100],"e":[100,100,100]},{"t":18.2431640625}]}},"ao":0,"shapes":[{"d":1,"ty":"el","s":{"k":[16,16]},"p":{"k":[0,0]},"nm":"Ellipse Path 1","mn":"ADBE Vector Shape - Ellipse"},{"ty":"fl","fillEnabled":true,"c":{"k":[1,1,1,1]},"o":{"k":100},"nm":"Fill 1","mn":"ADBE Vector Graphic - Fill"}],"ip":0,"op":60,"st":0,"bm":0,"sr":1},{"ddd":0,"ind":28,"ty":4,"nm":"12","ks":{"o":{"k":100},"r":{"k":0},"p":{"k":[77.5,182.5,0]},"a":{"k":[0,0,0]},"s":{"k":[{"i":{"x":[0.667,0.667,0.667],"y":[1,1,0.667]},"o":{"x":[0.333,0.333,0.333],"y":[0,0,0.333]},"n":["0p667_1_0p333_0","0p667_1_0p333_0","0p667_0p667_0p333_0p333"],"t":14.189,"s":[0,0,100],"e":[100,100,100]},{"t":18.2431640625}]}},"ao":0,"shapes":[{"d":1,"ty":"el","s":{"k":[16,16]},"p":{"k":[0,0]},"nm":"Ellipse Path 1","mn":"ADBE Vector Shape - Ellipse"},{"ty":"fl","fillEnabled":true,"c":{"k":[1,1,1,1]},"o":{"k":100},"nm":"Fill 1","mn":"ADBE Vector Graphic - Fill"}],"ip":0,"op":60,"st":0,"bm":0,"sr":1},{"ddd":0,"ind":29,"ty":4,"nm":"3 line 4","ks":{"o":{"k":100},"r":{"k":55},"p":{"k":[176.125,52.792,0]},"a":{"k":[-7.125,-374.75,0]},"s":{"k":[100,100,100]}},"ao":0,"shapes":[{"ty":"gr","it":[{"ind":0,"ty":"sh","ks":{"k":{"i":[[0,0],[0,0]],"o":[[0,0],[0,0]],"v":[[82.066,-261.331],[54.931,-317.564]],"c":false}},"nm":"Path 1","mn":"ADBE Vector Shape - Group"},{"ty":"tm","s":{"k":[{"i":{"x":[0.667],"y":[1]},"o":{"x":[0.333],"y":[0]},"n":["0p667_1_0p333_0"],"t":10.811,"s":[100],"e":[0]},{"t":14.865234375}],"ix":1},"e":{"k":100,"ix":2},"o":{"k":0,"ix":3},"m":1,"ix":2,"nm":"Trim Paths 1","mn":"ADBE Vector Filter - Trim"},{"ty":"st","fillEnabled":true,"c":{"k":[1,1,1,1]},"o":{"k":100},"w":{"k":2},"lc":1,"lj":1,"ml":4,"nm":"Stroke 1","mn":"ADBE Vector Graphic - Stroke"},{"ty":"fl","fillEnabled":true,"c":{"k":[1,1,1,1]},"o":{"k":100},"nm":"Fill 1","mn":"ADBE Vector Graphic - Fill"},{"ty":"tr","p":{"k":[-7.25,-374.5],"ix":2},"a":{"k":[-7.25,-374.5],"ix":1},"s":{"k":[100,100],"ix":3},"r":{"k":0,"ix":6},"o":{"k":100,"ix":7},"sk":{"k":0,"ix":4},"sa":{"k":0,"ix":5},"nm":"Transform"}],"nm":"Shape 1","np":4,"mn":"ADBE Vector Group"},{"ind":1,"ty":"sh","ks":{"k":{"i":[[0,0],[0,0]],"o":[[0,0],[0,0]],"v":[[0,0],[0,0]],"c":false}},"nm":"Path 1","mn":"ADBE Vector Shape - Group"},{"ty":"st","fillEnabled":true,"c":{"k":[1,1,1,1]},"o":{"k":100},"w":{"k":2},"lc":1,"lj":1,"ml":4,"nm":"Stroke 1","mn":"ADBE Vector Graphic - Stroke"}],"ip":0,"op":60,"st":0,"bm":0,"sr":1},{"ddd":0,"ind":30,"ty":4,"nm":"3 line 3","ks":{"o":{"k":100},"r":{"k":55},"p":{"k":[176.125,52.792,0]},"a":{"k":[-7.125,-374.75,0]},"s":{"k":[100,100,100]}},"ao":0,"shapes":[{"ty":"gr","it":[{"ind":0,"ty":"sh","ks":{"k":{"i":[[0,0],[0,0]],"o":[[0,0],[0,0]],"v":[[109.886,-310.215],[54.931,-317.564]],"c":false}},"nm":"Path 1","mn":"ADBE Vector Shape - Group"},{"ty":"tm","s":{"k":[{"i":{"x":[0.667],"y":[1]},"o":{"x":[0.333],"y":[0]},"n":["0p667_1_0p333_0"],"t":10.811,"s":[100],"e":[0]},{"t":14.865234375}],"ix":1},"e":{"k":100,"ix":2},"o":{"k":0,"ix":3},"m":1,"ix":2,"nm":"Trim Paths 1","mn":"ADBE Vector Filter - Trim"},{"ty":"st","fillEnabled":true,"c":{"k":[1,1,1,1]},"o":{"k":100},"w":{"k":2},"lc":1,"lj":1,"ml":4,"nm":"Stroke 1","mn":"ADBE Vector Graphic - Stroke"},{"ty":"fl","fillEnabled":true,"c":{"k":[1,1,1,1]},"o":{"k":100},"nm":"Fill 1","mn":"ADBE Vector Graphic - Fill"},{"ty":"tr","p":{"k":[-7.25,-374.5],"ix":2},"a":{"k":[-7.25,-374.5],"ix":1},"s":{"k":[100,100],"ix":3},"r":{"k":0,"ix":6},"o":{"k":100,"ix":7},"sk":{"k":0,"ix":4},"sa":{"k":0,"ix":5},"nm":"Transform"}],"nm":"Shape 1","np":4,"mn":"ADBE Vector Group"},{"ind":1,"ty":"sh","ks":{"k":{"i":[[0,0],[0,0]],"o":[[0,0],[0,0]],"v":[[0,0],[0,0]],"c":false}},"nm":"Path 1","mn":"ADBE Vector Shape - Group"},{"ty":"st","fillEnabled":true,"c":{"k":[1,1,1,1]},"o":{"k":100},"w":{"k":2},"lc":1,"lj":1,"ml":4,"nm":"Stroke 1","mn":"ADBE Vector Graphic - Stroke"}],"ip":0,"op":60,"st":0,"bm":0,"sr":1},{"ddd":0,"ind":31,"ty":4,"nm":"3 line 2","ks":{"o":{"k":100},"r":{"k":55},"p":{"k":[114.625,52.792,0]},"a":{"k":[-7.125,-374.75,0]},"s":{"k":[100,100,100]}},"ao":0,"shapes":[{"ty":"gr","it":[{"ind":0,"ty":"sh","ks":{"k":{"i":[[0,0],[0,0]],"o":[[0,0],[0,0]],"v":[[79.691,-266.656],[54.931,-317.564]],"c":false}},"nm":"Path 1","mn":"ADBE Vector Shape - Group"},{"ty":"tm","s":{"k":[{"i":{"x":[0.667],"y":[1]},"o":{"x":[0.333],"y":[0]},"n":["0p667_1_0p333_0"],"t":10.811,"s":[100],"e":[0]},{"t":14.865234375}],"ix":1},"e":{"k":100,"ix":2},"o":{"k":0,"ix":3},"m":1,"ix":2,"nm":"Trim Paths 1","mn":"ADBE Vector Filter - Trim"},{"ty":"st","fillEnabled":true,"c":{"k":[1,1,1,1]},"o":{"k":100},"w":{"k":2},"lc":1,"lj":1,"ml":4,"nm":"Stroke 1","mn":"ADBE Vector Graphic - Stroke"},{"ty":"fl","fillEnabled":true,"c":{"k":[1,1,1,1]},"o":{"k":100},"nm":"Fill 1","mn":"ADBE Vector Graphic - Fill"},{"ty":"tr","p":{"k":[-7.25,-374.5],"ix":2},"a":{"k":[-7.25,-374.5],"ix":1},"s":{"k":[100,100],"ix":3},"r":{"k":0,"ix":6},"o":{"k":100,"ix":7},"sk":{"k":0,"ix":4},"sa":{"k":0,"ix":5},"nm":"Transform"}],"nm":"Shape 1","np":4,"mn":"ADBE Vector Group"},{"ind":1,"ty":"sh","ks":{"k":{"i":[[0,0],[0,0]],"o":[[0,0],[0,0]],"v":[[0,0],[0,0]],"c":false}},"nm":"Path 1","mn":"ADBE Vector Shape - Group"},{"ty":"st","fillEnabled":true,"c":{"k":[1,1,1,1]},"o":{"k":100},"w":{"k":2},"lc":1,"lj":1,"ml":4,"nm":"Stroke 1","mn":"ADBE Vector Graphic - Stroke"}],"ip":0,"op":60,"st":0,"bm":0,"sr":1},{"ddd":0,"ind":32,"ty":4,"nm":"3 line","ks":{"o":{"k":100},"r":{"k":55},"p":{"k":[114.625,52.792,0]},"a":{"k":[-7.125,-374.75,0]},"s":{"k":[100,100,100]}},"ao":0,"shapes":[{"ty":"gr","it":[{"ind":0,"ty":"sh","ks":{"k":{"i":[[0,0],[0,0]],"o":[[0,0],[0,0]],"v":[[117.218,-312.405],[54.931,-317.564]],"c":false}},"nm":"Path 1","mn":"ADBE Vector Shape - Group"},{"ty":"tm","s":{"k":[{"i":{"x":[0.667],"y":[1]},"o":{"x":[0.333],"y":[0]},"n":["0p667_1_0p333_0"],"t":10.811,"s":[100],"e":[0]},{"t":14.865234375}],"ix":1},"e":{"k":100,"ix":2},"o":{"k":0,"ix":3},"m":1,"ix":2,"nm":"Trim Paths 1","mn":"ADBE Vector Filter - Trim"},{"ty":"st","fillEnabled":true,"c":{"k":[1,1,1,1]},"o":{"k":100},"w":{"k":2},"lc":1,"lj":1,"ml":4,"nm":"Stroke 1","mn":"ADBE Vector Graphic - Stroke"},{"ty":"fl","fillEnabled":true,"c":{"k":[1,1,1,1]},"o":{"k":100},"nm":"Fill 1","mn":"ADBE Vector Graphic - Fill"},{"ty":"tr","p":{"k":[-7.25,-374.5],"ix":2},"a":{"k":[-7.25,-374.5],"ix":1},"s":{"k":[100,100],"ix":3},"r":{"k":0,"ix":6},"o":{"k":100,"ix":7},"sk":{"k":0,"ix":4},"sa":{"k":0,"ix":5},"nm":"Transform"}],"nm":"Shape 1","np":4,"mn":"ADBE Vector Group"},{"ind":1,"ty":"sh","ks":{"k":{"i":[[0,0],[0,0]],"o":[[0,0],[0,0]],"v":[[0,0],[0,0]],"c":false}},"nm":"Path 1","mn":"ADBE Vector Shape - Group"},{"ty":"st","fillEnabled":true,"c":{"k":[1,1,1,1]},"o":{"k":100},"w":{"k":2},"lc":1,"lj":1,"ml":4,"nm":"Stroke 1","mn":"ADBE Vector Graphic - Stroke"}],"ip":0,"op":60,"st":0,"bm":0,"sr":1},{"ddd":0,"ind":33,"ty":4,"nm":"11","ks":{"o":{"k":100},"r":{"k":0},"p":{"k":[53.5,135,0]},"a":{"k":[0,0,0]},"s":{"k":[{"i":{"x":[0.667,0.667,0.667],"y":[1,1,0.667]},"o":{"x":[0.333,0.333,0.333],"y":[0,0,0.333]},"n":["0p667_1_0p333_0","0p667_1_0p333_0","0p667_0p667_0p333_0p333"],"t":12.162,"s":[0,0,100],"e":[100,100,100]},{"t":16.2158203125}]}},"ao":0,"shapes":[{"d":1,"ty":"el","s":{"k":[16,16]},"p":{"k":[0,0]},"nm":"Ellipse Path 1","mn":"ADBE Vector Shape - Ellipse"},{"ty":"fl","fillEnabled":true,"c":{"k":[1,1,1,1]},"o":{"k":100},"nm":"Fill 1","mn":"ADBE Vector Graphic - Fill"}],"ip":0,"op":60,"st":0,"bm":0,"sr":1},{"ddd":0,"ind":34,"ty":4,"nm":"10","ks":{"o":{"k":100},"r":{"k":0},"p":{"k":[213.75,135,0]},"a":{"k":[0,0,0]},"s":{"k":[{"i":{"x":[0.667,0.667,0.667],"y":[1,1,0.667]},"o":{"x":[0.333,0.333,0.333],"y":[0,0,0.333]},"n":["0p667_1_0p333_0","0p667_1_0p333_0","0p667_0p667_0p333_0p333"],"t":12.162,"s":[0,0,100],"e":[100,100,100]},{"t":16.2158203125}]}},"ao":0,"shapes":[{"d":1,"ty":"el","s":{"k":[16,16]},"p":{"k":[0,0]},"nm":"Ellipse Path 1","mn":"ADBE Vector Shape - Ellipse"},{"ty":"fl","fillEnabled":true,"c":{"k":[1,1,1,1]},"o":{"k":100},"nm":"Fill 1","mn":"ADBE Vector Graphic - Fill"}],"ip":0,"op":60,"st":0,"bm":0,"sr":1},{"ddd":0,"ind":35,"ty":4,"nm":"9","ks":{"o":{"k":100},"r":{"k":0},"p":{"k":[218.75,74.5,0]},"a":{"k":[0,0,0]},"s":{"k":[{"i":{"x":[0.667,0.667,0.667],"y":[1,1,0.667]},"o":{"x":[0.333,0.333,0.333],"y":[0,0,0.333]},"n":["0p667_1_0p333_0","0p667_1_0p333_0","0p667_0p667_0p333_0p333"],"t":12.162,"s":[0,0,100],"e":[100,100,100]},{"t":16.2158203125}]}},"ao":0,"shapes":[{"d":1,"ty":"el","s":{"k":[16,16]},"p":{"k":[0,0]},"nm":"Ellipse Path 1","mn":"ADBE Vector Shape - Ellipse"},{"ty":"fl","fillEnabled":true,"c":{"k":[1,1,1,1]},"o":{"k":100},"nm":"Fill 1","mn":"ADBE Vector Graphic - Fill"}],"ip":0,"op":60,"st":0,"bm":0,"sr":1},{"ddd":0,"ind":36,"ty":4,"nm":"8","ks":{"o":{"k":100},"r":{"k":0},"p":{"k":[50.5,74.5,0]},"a":{"k":[0,0,0]},"s":{"k":[{"i":{"x":[0.667,0.667,0.667],"y":[1,1,0.667]},"o":{"x":[0.333,0.333,0.333],"y":[0,0,0.333]},"n":["0p667_1_0p333_0","0p667_1_0p333_0","0p667_0p667_0p333_0p333"],"t":12.162,"s":[0,0,100],"e":[100,100,100]},{"t":16.2158203125}]}},"ao":0,"shapes":[{"d":1,"ty":"el","s":{"k":[16,16]},"p":{"k":[0,0]},"nm":"Ellipse Path 1","mn":"ADBE Vector Shape - Ellipse"},{"ty":"fl","fillEnabled":true,"c":{"k":[1,1,1,1]},"o":{"k":100},"nm":"Fill 1","mn":"ADBE Vector Graphic - Fill"}],"ip":0,"op":60,"st":0,"bm":0,"sr":1},{"ddd":0,"ind":37,"ty":4,"nm":"2 line 8","ks":{"o":{"k":100},"r":{"k":55},"p":{"k":[114.625,52.792,0]},"a":{"k":[-7.125,-374.75,0]},"s":{"k":[100,100,100]}},"ao":0,"shapes":[{"ty":"gr","it":[{"ind":0,"ty":"sh","ks":{"k":{"i":[[0,0],[0,0]],"o":[[0,0],[0,0]],"v":[[54.302,-318.005],[0.986,-324.207]],"c":false}},"nm":"Path 1","mn":"ADBE Vector Shape - Group"},{"ty":"tm","s":{"k":[{"i":{"x":[0.667],"y":[1]},"o":{"x":[0.333],"y":[0]},"n":["0p667_1_0p333_0"],"t":8.784,"s":[100],"e":[0]},{"t":12.837890625}],"ix":1},"e":{"k":100,"ix":2},"o":{"k":0,"ix":3},"m":1,"ix":2,"nm":"Trim Paths 1","mn":"ADBE Vector Filter - Trim"},{"ty":"st","fillEnabled":true,"c":{"k":[1,1,1,1]},"o":{"k":100},"w":{"k":2},"lc":1,"lj":1,"ml":4,"nm":"Stroke 1","mn":"ADBE Vector Graphic - Stroke"},{"ty":"fl","fillEnabled":true,"c":{"k":[1,1,1,1]},"o":{"k":100},"nm":"Fill 1","mn":"ADBE Vector Graphic - Fill"},{"ty":"tr","p":{"k":[-7.25,-374.5],"ix":2},"a":{"k":[-7.25,-374.5],"ix":1},"s":{"k":[100,100],"ix":3},"r":{"k":0,"ix":6},"o":{"k":100,"ix":7},"sk":{"k":0,"ix":4},"sa":{"k":0,"ix":5},"nm":"Transform"}],"nm":"Shape 1","np":4,"mn":"ADBE Vector Group"},{"ind":1,"ty":"sh","ks":{"k":{"i":[[0,0],[0,0]],"o":[[0,0],[0,0]],"v":[[0,0],[0,0]],"c":false}},"nm":"Path 1","mn":"ADBE Vector Shape - Group"},{"ty":"st","fillEnabled":true,"c":{"k":[1,1,1,1]},"o":{"k":100},"w":{"k":2},"lc":1,"lj":1,"ml":4,"nm":"Stroke 1","mn":"ADBE Vector Graphic - Stroke"}],"ip":0,"op":60,"st":0,"bm":0,"sr":1},{"ddd":0,"ind":38,"ty":4,"nm":"2 line 7","ks":{"o":{"k":100},"r":{"k":55},"p":{"k":[114.625,52.792,0]},"a":{"k":[-7.125,-374.75,0]},"s":{"k":[100,100,100]}},"ao":0,"shapes":[{"ty":"gr","it":[{"ind":0,"ty":"sh","ks":{"k":{"i":[[0,0],[0,0]],"o":[[0,0],[0,0]],"v":[[26.831,-275.286],[0.986,-324.207]],"c":false}},"nm":"Path 1","mn":"ADBE Vector Shape - Group"},{"ty":"tm","s":{"k":[{"i":{"x":[0.667],"y":[1]},"o":{"x":[0.333],"y":[0]},"n":["0p667_1_0p333_0"],"t":8.784,"s":[100],"e":[0]},{"t":12.837890625}],"ix":1},"e":{"k":100,"ix":2},"o":{"k":0,"ix":3},"m":1,"ix":2,"nm":"Trim Paths 1","mn":"ADBE Vector Filter - Trim"},{"ty":"st","fillEnabled":true,"c":{"k":[1,1,1,1]},"o":{"k":100},"w":{"k":2},"lc":1,"lj":1,"ml":4,"nm":"Stroke 1","mn":"ADBE Vector Graphic - Stroke"},{"ty":"fl","fillEnabled":true,"c":{"k":[1,1,1,1]},"o":{"k":100},"nm":"Fill 1","mn":"ADBE Vector Graphic - Fill"},{"ty":"tr","p":{"k":[-7.25,-374.5],"ix":2},"a":{"k":[-7.25,-374.5],"ix":1},"s":{"k":[100,100],"ix":3},"r":{"k":0,"ix":6},"o":{"k":100,"ix":7},"sk":{"k":0,"ix":4},"sa":{"k":0,"ix":5},"nm":"Transform"}],"nm":"Shape 1","np":4,"mn":"ADBE Vector Group"},{"ind":1,"ty":"sh","ks":{"k":{"i":[[0,0],[0,0]],"o":[[0,0],[0,0]],"v":[[0,0],[0,0]],"c":false}},"nm":"Path 1","mn":"ADBE Vector Shape - Group"},{"ty":"st","fillEnabled":true,"c":{"k":[1,1,1,1]},"o":{"k":100},"w":{"k":2},"lc":1,"lj":1,"ml":4,"nm":"Stroke 1","mn":"ADBE Vector Graphic - Stroke"}],"ip":0,"op":60,"st":0,"bm":0,"sr":1},{"ddd":0,"ind":39,"ty":4,"nm":"2 line 6","ks":{"o":{"k":100},"r":{"k":55},"p":{"k":[114.625,52.792,0]},"a":{"k":[-7.125,-374.75,0]},"s":{"k":[100,100,100]}},"ao":0,"shapes":[{"ty":"gr","it":[{"ind":0,"ty":"sh","ks":{"k":{"i":[[0,0],[0,0]],"o":[[0,0],[0,0]],"v":[[-26.414,-309.517],[0.986,-324.207]],"c":false}},"nm":"Path 1","mn":"ADBE Vector Shape - Group"},{"ty":"tm","s":{"k":[{"i":{"x":[0.667],"y":[1]},"o":{"x":[0.333],"y":[0]},"n":["0p667_1_0p333_0"],"t":8.784,"s":[100],"e":[0]},{"t":12.837890625}],"ix":1},"e":{"k":100,"ix":2},"o":{"k":0,"ix":3},"m":1,"ix":2,"nm":"Trim Paths 1","mn":"ADBE Vector Filter - Trim"},{"ty":"st","fillEnabled":true,"c":{"k":[1,1,1,1]},"o":{"k":100},"w":{"k":2},"lc":1,"lj":1,"ml":4,"nm":"Stroke 1","mn":"ADBE Vector Graphic - Stroke"},{"ty":"fl","fillEnabled":true,"c":{"k":[1,1,1,1]},"o":{"k":100},"nm":"Fill 1","mn":"ADBE Vector Graphic - Fill"},{"ty":"tr","p":{"k":[-7.25,-374.5],"ix":2},"a":{"k":[-7.25,-374.5],"ix":1},"s":{"k":[100,100],"ix":3},"r":{"k":0,"ix":6},"o":{"k":100,"ix":7},"sk":{"k":0,"ix":4},"sa":{"k":0,"ix":5},"nm":"Transform"}],"nm":"Shape 1","np":4,"mn":"ADBE Vector Group"},{"ind":1,"ty":"sh","ks":{"k":{"i":[[0,0],[0,0]],"o":[[0,0],[0,0]],"v":[[0,0],[0,0]],"c":false}},"nm":"Path 1","mn":"ADBE Vector Shape - Group"},{"ty":"st","fillEnabled":true,"c":{"k":[1,1,1,1]},"o":{"k":100},"w":{"k":2},"lc":1,"lj":1,"ml":4,"nm":"Stroke 1","mn":"ADBE Vector Graphic - Stroke"}],"ip":0,"op":60,"st":0,"bm":0,"sr":1},{"ddd":0,"ind":40,"ty":4,"nm":"2 line 5","ks":{"o":{"k":100},"r":{"k":55},"p":{"k":[114.625,52.792,0]},"a":{"k":[-7.125,-374.75,0]},"s":{"k":[100,100,100]}},"ao":0,"shapes":[{"ty":"gr","it":[{"ind":0,"ty":"sh","ks":{"k":{"i":[[0,0],[0,0]],"o":[[0,0],[0,0]],"v":[[-27.184,-372.926],[0.986,-324.207]],"c":false}},"nm":"Path 1","mn":"ADBE Vector Shape - Group"},{"ty":"tm","s":{"k":[{"i":{"x":[0.667],"y":[1]},"o":{"x":[0.333],"y":[0]},"n":["0p667_1_0p333_0"],"t":8.784,"s":[100],"e":[0]},{"t":12.837890625}],"ix":1},"e":{"k":100,"ix":2},"o":{"k":0,"ix":3},"m":1,"ix":2,"nm":"Trim Paths 1","mn":"ADBE Vector Filter - Trim"},{"ty":"st","fillEnabled":true,"c":{"k":[1,1,1,1]},"o":{"k":100},"w":{"k":2},"lc":1,"lj":1,"ml":4,"nm":"Stroke 1","mn":"ADBE Vector Graphic - Stroke"},{"ty":"fl","fillEnabled":true,"c":{"k":[1,1,1,1]},"o":{"k":100},"nm":"Fill 1","mn":"ADBE Vector Graphic - Fill"},{"ty":"tr","p":{"k":[-7.25,-374.5],"ix":2},"a":{"k":[-7.25,-374.5],"ix":1},"s":{"k":[100,100],"ix":3},"r":{"k":0,"ix":6},"o":{"k":100,"ix":7},"sk":{"k":0,"ix":4},"sa":{"k":0,"ix":5},"nm":"Transform"}],"nm":"Shape 1","np":4,"mn":"ADBE Vector Group"},{"ind":1,"ty":"sh","ks":{"k":{"i":[[0,0],[0,0]],"o":[[0,0],[0,0]],"v":[[0,0],[0,0]],"c":false}},"nm":"Path 1","mn":"ADBE Vector Shape - Group"},{"ty":"st","fillEnabled":true,"c":{"k":[1,1,1,1]},"o":{"k":100},"w":{"k":2},"lc":1,"lj":1,"ml":4,"nm":"Stroke 1","mn":"ADBE Vector Graphic - Stroke"}],"ip":0,"op":60,"st":0,"bm":0,"sr":1},{"ddd":0,"ind":41,"ty":4,"nm":"2 line 4","ks":{"o":{"k":100},"r":{"k":55},"p":{"k":[114.625,52.792,0]},"a":{"k":[-7.125,-374.75,0]},"s":{"k":[100,100,100]}},"ao":0,"shapes":[{"ty":"gr","it":[{"ind":0,"ty":"sh","ks":{"k":{"i":[[0,0],[0,0]],"o":[[0,0],[0,0]],"v":[[90.273,-368.506],[64.899,-416.792]],"c":false}},"nm":"Path 1","mn":"ADBE Vector Shape - Group"},{"ty":"tm","s":{"k":[{"i":{"x":[0.667],"y":[1]},"o":{"x":[0.333],"y":[0]},"n":["0p667_1_0p333_0"],"t":8.784,"s":[100],"e":[0]},{"t":12.837890625}],"ix":1},"e":{"k":100,"ix":2},"o":{"k":0,"ix":3},"m":1,"ix":2,"nm":"Trim Paths 1","mn":"ADBE Vector Filter - Trim"},{"ty":"st","fillEnabled":true,"c":{"k":[1,1,1,1]},"o":{"k":100},"w":{"k":2},"lc":1,"lj":1,"ml":4,"nm":"Stroke 1","mn":"ADBE Vector Graphic - Stroke"},{"ty":"fl","fillEnabled":true,"c":{"k":[1,1,1,1]},"o":{"k":100},"nm":"Fill 1","mn":"ADBE Vector Graphic - Fill"},{"ty":"tr","p":{"k":[-7.25,-374.5],"ix":2},"a":{"k":[-7.25,-374.5],"ix":1},"s":{"k":[100,100],"ix":3},"r":{"k":0,"ix":6},"o":{"k":100,"ix":7},"sk":{"k":0,"ix":4},"sa":{"k":0,"ix":5},"nm":"Transform"}],"nm":"Shape 1","np":4,"mn":"ADBE Vector Group"},{"ind":1,"ty":"sh","ks":{"k":{"i":[[0,0],[0,0]],"o":[[0,0],[0,0]],"v":[[0,0],[0,0]],"c":false}},"nm":"Path 1","mn":"ADBE Vector Shape - Group"},{"ty":"st","fillEnabled":true,"c":{"k":[1,1,1,1]},"o":{"k":100},"w":{"k":2},"lc":1,"lj":1,"ml":4,"nm":"Stroke 1","mn":"ADBE Vector Graphic - Stroke"}],"ip":0,"op":60,"st":0,"bm":0,"sr":1},{"ddd":0,"ind":42,"ty":4,"nm":"2 line 3","ks":{"o":{"k":100},"r":{"k":55},"p":{"k":[114.625,52.792,0]},"a":{"k":[-7.125,-374.75,0]},"s":{"k":[100,100,100]}},"ao":0,"shapes":[{"ty":"gr","it":[{"ind":0,"ty":"sh","ks":{"k":{"i":[[0,0],[0,0]],"o":[[0,0],[0,0]],"v":[[118.604,-409.402],[64.899,-416.792]],"c":false}},"nm":"Path 1","mn":"ADBE Vector Shape - Group"},{"ty":"tm","s":{"k":[{"i":{"x":[0.667],"y":[1]},"o":{"x":[0.333],"y":[0]},"n":["0p667_1_0p333_0"],"t":8.784,"s":[100],"e":[0]},{"t":12.837890625}],"ix":1},"e":{"k":100,"ix":2},"o":{"k":0,"ix":3},"m":1,"ix":2,"nm":"Trim Paths 1","mn":"ADBE Vector Filter - Trim"},{"ty":"st","fillEnabled":true,"c":{"k":[1,1,1,1]},"o":{"k":100},"w":{"k":2},"lc":1,"lj":1,"ml":4,"nm":"Stroke 1","mn":"ADBE Vector Graphic - Stroke"},{"ty":"fl","fillEnabled":true,"c":{"k":[1,1,1,1]},"o":{"k":100},"nm":"Fill 1","mn":"ADBE Vector Graphic - Fill"},{"ty":"tr","p":{"k":[-7.25,-374.5],"ix":2},"a":{"k":[-7.25,-374.5],"ix":1},"s":{"k":[100,100],"ix":3},"r":{"k":0,"ix":6},"o":{"k":100,"ix":7},"sk":{"k":0,"ix":4},"sa":{"k":0,"ix":5},"nm":"Transform"}],"nm":"Shape 1","np":4,"mn":"ADBE Vector Group"},{"ind":1,"ty":"sh","ks":{"k":{"i":[[0,0],[0,0]],"o":[[0,0],[0,0]],"v":[[0,0],[0,0]],"c":false}},"nm":"Path 1","mn":"ADBE Vector Shape - Group"},{"ty":"st","fillEnabled":true,"c":{"k":[1,1,1,1]},"o":{"k":100},"w":{"k":2},"lc":1,"lj":1,"ml":4,"nm":"Stroke 1","mn":"ADBE Vector Graphic - Stroke"}],"ip":0,"op":60,"st":0,"bm":0,"sr":1},{"ddd":0,"ind":43,"ty":4,"nm":"2 line 2","ks":{"o":{"k":100},"r":{"k":55},"p":{"k":[114.625,52.792,0]},"a":{"k":[-7.125,-374.75,0]},"s":{"k":[100,100,100]}},"ao":0,"shapes":[{"ty":"gr","it":[{"ind":0,"ty":"sh","ks":{"k":{"i":[[0,0],[0,0]],"o":[[0,0],[0,0]],"v":[[9.423,-426.949],[64.899,-416.792]],"c":false}},"nm":"Path 1","mn":"ADBE Vector Shape - Group"},{"ty":"tm","s":{"k":[{"i":{"x":[0.667],"y":[1]},"o":{"x":[0.333],"y":[0]},"n":["0p667_1_0p333_0"],"t":8.784,"s":[100],"e":[0]},{"t":12.837890625}],"ix":1},"e":{"k":100,"ix":2},"o":{"k":0,"ix":3},"m":1,"ix":2,"nm":"Trim Paths 1","mn":"ADBE Vector Filter - Trim"},{"ty":"st","fillEnabled":true,"c":{"k":[1,1,1,1]},"o":{"k":100},"w":{"k":2},"lc":1,"lj":1,"ml":4,"nm":"Stroke 1","mn":"ADBE Vector Graphic - Stroke"},{"ty":"fl","fillEnabled":true,"c":{"k":[1,1,1,1]},"o":{"k":100},"nm":"Fill 1","mn":"ADBE Vector Graphic - Fill"},{"ty":"tr","p":{"k":[-7.25,-374.5],"ix":2},"a":{"k":[-7.25,-374.5],"ix":1},"s":{"k":[100,100],"ix":3},"r":{"k":0,"ix":6},"o":{"k":100,"ix":7},"sk":{"k":0,"ix":4},"sa":{"k":0,"ix":5},"nm":"Transform"}],"nm":"Shape 1","np":4,"mn":"ADBE Vector Group"},{"ind":1,"ty":"sh","ks":{"k":{"i":[[0,0],[0,0]],"o":[[0,0],[0,0]],"v":[[0,0],[0,0]],"c":false}},"nm":"Path 1","mn":"ADBE Vector Shape - Group"},{"ty":"st","fillEnabled":true,"c":{"k":[1,1,1,1]},"o":{"k":100},"w":{"k":2},"lc":1,"lj":1,"ml":4,"nm":"Stroke 1","mn":"ADBE Vector Graphic - Stroke"}],"ip":0,"op":60,"st":0,"bm":0,"sr":1},{"ddd":0,"ind":44,"ty":4,"nm":"2 line","ks":{"o":{"k":100},"r":{"k":55},"p":{"k":[114.625,52.792,0]},"a":{"k":[-7.125,-374.75,0]},"s":{"k":[100,100,100]}},"ao":0,"shapes":[{"ty":"gr","it":[{"ind":0,"ty":"sh","ks":{"k":{"i":[[0,0],[0,0]],"o":[[0,0],[0,0]],"v":[[70.889,-448.916],[64.899,-416.792]],"c":false}},"nm":"Path 1","mn":"ADBE Vector Shape - Group"},{"ty":"tm","s":{"k":[{"i":{"x":[0.667],"y":[1]},"o":{"x":[0.333],"y":[0]},"n":["0p667_1_0p333_0"],"t":8.784,"s":[100],"e":[0]},{"t":12.837890625}],"ix":1},"e":{"k":100,"ix":2},"o":{"k":0,"ix":3},"m":1,"ix":2,"nm":"Trim Paths 1","mn":"ADBE Vector Filter - Trim"},{"ty":"st","fillEnabled":true,"c":{"k":[1,1,1,1]},"o":{"k":100},"w":{"k":2},"lc":1,"lj":1,"ml":4,"nm":"Stroke 1","mn":"ADBE Vector Graphic - Stroke"},{"ty":"fl","fillEnabled":true,"c":{"k":[1,1,1,1]},"o":{"k":100},"nm":"Fill 1","mn":"ADBE Vector Graphic - Fill"},{"ty":"tr","p":{"k":[-7.25,-374.5],"ix":2},"a":{"k":[-7.25,-374.5],"ix":1},"s":{"k":[100,100],"ix":3},"r":{"k":0,"ix":6},"o":{"k":100,"ix":7},"sk":{"k":0,"ix":4},"sa":{"k":0,"ix":5},"nm":"Transform"}],"nm":"Shape 1","np":4,"mn":"ADBE Vector Group"},{"ind":1,"ty":"sh","ks":{"k":{"i":[[0,0],[0,0]],"o":[[0,0],[0,0]],"v":[[0,0],[0,0]],"c":false}},"nm":"Path 1","mn":"ADBE Vector Shape - Group"},{"ty":"st","fillEnabled":true,"c":{"k":[1,1,1,1]},"o":{"k":100},"w":{"k":2},"lc":1,"lj":1,"ml":4,"nm":"Stroke 1","mn":"ADBE Vector Graphic - Stroke"}],"ip":0,"op":60,"st":0,"bm":0,"sr":1},{"ddd":0,"ind":45,"ty":4,"nm":"1 line 6","ks":{"o":{"k":100},"r":{"k":55},"p":{"k":[114.625,52.792,0]},"a":{"k":[-7.125,-374.75,0]},"s":{"k":[100,100,100]}},"ao":0,"shapes":[{"ty":"gr","it":[{"ind":0,"ty":"sh","ks":{"k":{"i":[[0,0],[0,0]],"o":[[0,0],[0,0]],"v":[[67.239,-419.732],[26,-374.75]],"c":false}},"nm":"Path 1","mn":"ADBE Vector Shape - Group"},{"ty":"tm","s":{"k":[{"i":{"x":[0.667],"y":[1]},"o":{"x":[0.333],"y":[0]},"n":["0p667_1_0p333_0"],"t":2.027,"s":[100],"e":[0]},{"t":6.0810546875}],"ix":1},"e":{"k":100,"ix":2},"o":{"k":0,"ix":3},"m":1,"ix":2,"nm":"Trim Paths 1","mn":"ADBE Vector Filter - Trim"},{"ty":"st","fillEnabled":true,"c":{"k":[1,1,1,1]},"o":{"k":100},"w":{"k":2},"lc":1,"lj":1,"ml":4,"nm":"Stroke 1","mn":"ADBE Vector Graphic - Stroke"},{"ty":"fl","fillEnabled":true,"c":{"k":[1,1,1,1]},"o":{"k":100},"nm":"Fill 1","mn":"ADBE Vector Graphic - Fill"},{"ty":"tr","p":{"k":[-7.25,-374.5],"ix":2},"a":{"k":[-7.25,-374.5],"ix":1},"s":{"k":[100,100],"ix":3},"r":{"k":0,"ix":6},"o":{"k":100,"ix":7},"sk":{"k":0,"ix":4},"sa":{"k":0,"ix":5},"nm":"Transform"}],"nm":"Shape 1","np":4,"mn":"ADBE Vector Group"},{"ind":1,"ty":"sh","ks":{"k":{"i":[[0,0],[0,0]],"o":[[0,0],[0,0]],"v":[[0,0],[0,0]],"c":false}},"nm":"Path 1","mn":"ADBE Vector Shape - Group"},{"ty":"st","fillEnabled":true,"c":{"k":[1,1,1,1]},"o":{"k":100},"w":{"k":2},"lc":1,"lj":1,"ml":4,"nm":"Stroke 1","mn":"ADBE Vector Graphic - Stroke"}],"ip":0,"op":60,"st":0,"bm":0,"sr":1},{"ddd":0,"ind":46,"ty":4,"nm":"1 line 5","ks":{"o":{"k":100},"r":{"k":55},"p":{"k":[114.625,52.792,0]},"a":{"k":[-7.125,-374.75,0]},"s":{"k":[100,100,100]}},"ao":0,"shapes":[{"ty":"gr","it":[{"ind":0,"ty":"sh","ks":{"k":{"i":[[0,0],[0,0]],"o":[[0,0],[0,0]],"v":[[-2.532,-322.703],[26,-374.75]],"c":false}},"nm":"Path 1","mn":"ADBE Vector Shape - Group"},{"ty":"tm","s":{"k":[{"i":{"x":[0.667],"y":[1]},"o":{"x":[0.333],"y":[0]},"n":["0p667_1_0p333_0"],"t":2.027,"s":[100],"e":[0]},{"t":6.0810546875}],"ix":1},"e":{"k":100,"ix":2},"o":{"k":0,"ix":3},"m":1,"ix":2,"nm":"Trim Paths 1","mn":"ADBE Vector Filter - Trim"},{"ty":"st","fillEnabled":true,"c":{"k":[1,1,1,1]},"o":{"k":100},"w":{"k":2},"lc":1,"lj":1,"ml":4,"nm":"Stroke 1","mn":"ADBE Vector Graphic - Stroke"},{"ty":"fl","fillEnabled":true,"c":{"k":[1,1,1,1]},"o":{"k":100},"nm":"Fill 1","mn":"ADBE Vector Graphic - Fill"},{"ty":"tr","p":{"k":[-7.25,-374.5],"ix":2},"a":{"k":[-7.25,-374.5],"ix":1},"s":{"k":[100,100],"ix":3},"r":{"k":0,"ix":6},"o":{"k":100,"ix":7},"sk":{"k":0,"ix":4},"sa":{"k":0,"ix":5},"nm":"Transform"}],"nm":"Shape 1","np":4,"mn":"ADBE Vector Group"},{"ind":1,"ty":"sh","ks":{"k":{"i":[[0,0],[0,0]],"o":[[0,0],[0,0]],"v":[[0,0],[0,0]],"c":false}},"nm":"Path 1","mn":"ADBE Vector Shape - Group"},{"ty":"st","fillEnabled":true,"c":{"k":[1,1,1,1]},"o":{"k":100},"w":{"k":2},"lc":1,"lj":1,"ml":4,"nm":"Stroke 1","mn":"ADBE Vector Graphic - Stroke"}],"ip":0,"op":60,"st":0,"bm":0,"sr":1},{"ddd":0,"ind":47,"ty":4,"nm":"1 line 4","ks":{"o":{"k":100},"r":{"k":55},"p":{"k":[114.625,52.792,0]},"a":{"k":[-7.125,-374.75,0]},"s":{"k":[100,100,100]}},"ao":0,"shapes":[{"ty":"gr","it":[{"ind":0,"ty":"sh","ks":{"k":{"i":[[0,0],[0,0]],"o":[[0,0],[0,0]],"v":[[53.38,-317.125],[26,-374.75]],"c":false}},"nm":"Path 1","mn":"ADBE Vector Shape - Group"},{"ty":"tm","s":{"k":[{"i":{"x":[0.667],"y":[1]},"o":{"x":[0.333],"y":[0]},"n":["0p667_1_0p333_0"],"t":2.027,"s":[100],"e":[0]},{"t":6.0810546875}],"ix":1},"e":{"k":100,"ix":2},"o":{"k":0,"ix":3},"m":1,"ix":2,"nm":"Trim Paths 1","mn":"ADBE Vector Filter - Trim"},{"ty":"st","fillEnabled":true,"c":{"k":[1,1,1,1]},"o":{"k":100},"w":{"k":2},"lc":1,"lj":1,"ml":4,"nm":"Stroke 1","mn":"ADBE Vector Graphic - Stroke"},{"ty":"fl","fillEnabled":true,"c":{"k":[1,1,1,1]},"o":{"k":100},"nm":"Fill 1","mn":"ADBE Vector Graphic - Fill"},{"ty":"tr","p":{"k":[-7.25,-374.5],"ix":2},"a":{"k":[-7.25,-374.5],"ix":1},"s":{"k":[100,100],"ix":3},"r":{"k":0,"ix":6},"o":{"k":100,"ix":7},"sk":{"k":0,"ix":4},"sa":{"k":0,"ix":5},"nm":"Transform"}],"nm":"Shape 1","np":4,"mn":"ADBE Vector Group"},{"ind":1,"ty":"sh","ks":{"k":{"i":[[0,0],[0,0]],"o":[[0,0],[0,0]],"v":[[0,0],[0,0]],"c":false}},"nm":"Path 1","mn":"ADBE Vector Shape - Group"},{"ty":"st","fillEnabled":true,"c":{"k":[1,1,1,1]},"o":{"k":100},"w":{"k":2},"lc":1,"lj":1,"ml":4,"nm":"Stroke 1","mn":"ADBE Vector Graphic - Stroke"}],"ip":0,"op":60,"st":0,"bm":0,"sr":1},{"ddd":0,"ind":48,"ty":4,"nm":"1 line 3","ks":{"o":{"k":100},"r":{"k":55},"p":{"k":[114.625,52.792,0]},"a":{"k":[-7.125,-374.75,0]},"s":{"k":[100,100,100]}},"ao":0,"shapes":[{"ty":"gr","it":[{"ind":0,"ty":"sh","ks":{"k":{"i":[[0,0],[0,0]],"o":[[0,0],[0,0]],"v":[[91.195,-369.386],[26,-374.75]],"c":false}},"nm":"Path 1","mn":"ADBE Vector Shape - Group"},{"ty":"tm","s":{"k":[{"i":{"x":[0.667],"y":[1]},"o":{"x":[0.333],"y":[0]},"n":["0p667_1_0p333_0"],"t":2.027,"s":[100],"e":[0]},{"t":6.0810546875}],"ix":1},"e":{"k":100,"ix":2},"o":{"k":0,"ix":3},"m":1,"ix":2,"nm":"Trim Paths 1","mn":"ADBE Vector Filter - Trim"},{"ty":"st","fillEnabled":true,"c":{"k":[1,1,1,1]},"o":{"k":100},"w":{"k":2},"lc":1,"lj":1,"ml":4,"nm":"Stroke 1","mn":"ADBE Vector Graphic - Stroke"},{"ty":"fl","fillEnabled":true,"c":{"k":[1,1,1,1]},"o":{"k":100},"nm":"Fill 1","mn":"ADBE Vector Graphic - Fill"},{"ty":"tr","p":{"k":[-7.25,-374.5],"ix":2},"a":{"k":[-7.25,-374.5],"ix":1},"s":{"k":[100,100],"ix":3},"r":{"k":0,"ix":6},"o":{"k":100,"ix":7},"sk":{"k":0,"ix":4},"sa":{"k":0,"ix":5},"nm":"Transform"}],"nm":"Shape 1","np":4,"mn":"ADBE Vector Group"},{"ind":1,"ty":"sh","ks":{"k":{"i":[[0,0],[0,0]],"o":[[0,0],[0,0]],"v":[[0,0],[0,0]],"c":false}},"nm":"Path 1","mn":"ADBE Vector Shape - Group"},{"ty":"st","fillEnabled":true,"c":{"k":[1,1,1,1]},"o":{"k":100},"w":{"k":2},"lc":1,"lj":1,"ml":4,"nm":"Stroke 1","mn":"ADBE Vector Graphic - Stroke"}],"ip":0,"op":60,"st":0,"bm":0,"sr":1},{"ddd":0,"ind":49,"ty":4,"nm":"1 line 2","ks":{"o":{"k":100},"r":{"k":55},"p":{"k":[114.625,52.792,0]},"a":{"k":[-7.125,-374.75,0]},"s":{"k":[100,100,100]}},"ao":0,"shapes":[{"ty":"gr","it":[{"ind":0,"ty":"sh","ks":{"k":{"i":[[0,0],[0,0]],"o":[[0,0],[0,0]],"v":[[11.594,-427.87],[26,-374.75]],"c":false}},"nm":"Path 1","mn":"ADBE Vector Shape - Group"},{"ty":"tm","s":{"k":[{"i":{"x":[0.667],"y":[1]},"o":{"x":[0.333],"y":[0]},"n":["0p667_1_0p333_0"],"t":2.027,"s":[100],"e":[0]},{"t":6.0810546875}],"ix":1},"e":{"k":100,"ix":2},"o":{"k":0,"ix":3},"m":1,"ix":2,"nm":"Trim Paths 1","mn":"ADBE Vector Filter - Trim"},{"ty":"st","fillEnabled":true,"c":{"k":[1,1,1,1]},"o":{"k":100},"w":{"k":2},"lc":1,"lj":1,"ml":4,"nm":"Stroke 1","mn":"ADBE Vector Graphic - Stroke"},{"ty":"fl","fillEnabled":true,"c":{"k":[1,1,1,1]},"o":{"k":100},"nm":"Fill 1","mn":"ADBE Vector Graphic - Fill"},{"ty":"tr","p":{"k":[-7.25,-374.5],"ix":2},"a":{"k":[-7.25,-374.5],"ix":1},"s":{"k":[100,100],"ix":3},"r":{"k":0,"ix":6},"o":{"k":100,"ix":7},"sk":{"k":0,"ix":4},"sa":{"k":0,"ix":5},"nm":"Transform"}],"nm":"Shape 1","np":4,"mn":"ADBE Vector Group"},{"ind":1,"ty":"sh","ks":{"k":{"i":[[0,0],[0,0]],"o":[[0,0],[0,0]],"v":[[0,0],[0,0]],"c":false}},"nm":"Path 1","mn":"ADBE Vector Shape - Group"},{"ty":"st","fillEnabled":true,"c":{"k":[1,1,1,1]},"o":{"k":100},"w":{"k":2},"lc":1,"lj":1,"ml":4,"nm":"Stroke 1","mn":"ADBE Vector Graphic - Stroke"}],"ip":0,"op":60,"st":0,"bm":0,"sr":1},{"ddd":0,"ind":50,"ty":4,"nm":"1 line","ks":{"o":{"k":100},"r":{"k":55},"p":{"k":[114.625,52.792,0]},"a":{"k":[-7.125,-374.75,0]},"s":{"k":[100,100,100]}},"ao":0,"shapes":[{"ty":"gr","it":[{"ind":0,"ty":"sh","ks":{"k":{"i":[[0,0],[0,0]],"o":[[0,0],[0,0]],"v":[[-26.979,-372.782],[26,-374.75]],"c":false}},"nm":"Path 1","mn":"ADBE Vector Shape - Group"},{"ty":"tm","s":{"k":[{"i":{"x":[0.667],"y":[1]},"o":{"x":[0.333],"y":[0]},"n":["0p667_1_0p333_0"],"t":2.027,"s":[100],"e":[0]},{"t":6.0810546875}],"ix":1},"e":{"k":100,"ix":2},"o":{"k":0,"ix":3},"m":1,"ix":2,"nm":"Trim Paths 1","mn":"ADBE Vector Filter - Trim"},{"ty":"st","fillEnabled":true,"c":{"k":[1,1,1,1]},"o":{"k":100},"w":{"k":2},"lc":1,"lj":1,"ml":4,"nm":"Stroke 1","mn":"ADBE Vector Graphic - Stroke"},{"ty":"fl","fillEnabled":true,"c":{"k":[1,1,1,1]},"o":{"k":100},"nm":"Fill 1","mn":"ADBE Vector Graphic - Fill"},{"ty":"tr","p":{"k":[-7.25,-374.5],"ix":2},"a":{"k":[-7.25,-374.5],"ix":1},"s":{"k":[100,100],"ix":3},"r":{"k":0,"ix":6},"o":{"k":100,"ix":7},"sk":{"k":0,"ix":4},"sa":{"k":0,"ix":5},"nm":"Transform"}],"nm":"Shape 1","np":4,"mn":"ADBE Vector Group"},{"ind":1,"ty":"sh","ks":{"k":{"i":[[0,0],[0,0]],"o":[[0,0],[0,0]],"v":[[0,0],[0,0]],"c":false}},"nm":"Path 1","mn":"ADBE Vector Shape - Group"},{"ty":"st","fillEnabled":true,"c":{"k":[1,1,1,1]},"o":{"k":100},"w":{"k":2},"lc":1,"lj":1,"ml":4,"nm":"Stroke 1","mn":"ADBE Vector Graphic - Stroke"}],"ip":0,"op":60,"st":0,"bm":0,"sr":1},{"ddd":0,"ind":51,"ty":4,"nm":"7","ks":{"o":{"k":100},"r":{"k":0},"p":{"k":[165.5,135.5,0]},"a":{"k":[0,0,0]},"s":{"k":[{"i":{"x":[0.667,0.667,0.667],"y":[1,1,0.667]},"o":{"x":[0.333,0.333,0.333],"y":[0,0,0.333]},"n":["0p667_1_0p333_0","0p667_1_0p333_0","0p667_0p667_0p333_0p333"],"t":5.405,"s":[0,0,100],"e":[100,100,100]},{"t":9.458984375}]}},"ao":0,"shapes":[{"d":1,"ty":"el","s":{"k":[16,16]},"p":{"k":[0,0]},"nm":"Ellipse Path 1","mn":"ADBE Vector Shape - Ellipse"},{"ty":"fl","fillEnabled":true,"c":{"k":[1,1,1,1]},"o":{"k":100},"nm":"Fill 1","mn":"ADBE Vector Graphic - Fill"}],"ip":0,"op":60,"st":0,"bm":0,"sr":1},{"ddd":0,"ind":52,"ty":4,"nm":"6","ks":{"o":{"k":100},"r":{"k":0},"p":{"k":[102.5,135.5,0]},"a":{"k":[0,0,0]},"s":{"k":[{"i":{"x":[0.667,0.667,0.667],"y":[1,1,0.667]},"o":{"x":[0.333,0.333,0.333],"y":[0,0,0.333]},"n":["0p667_1_0p333_0","0p667_1_0p333_0","0p667_0p667_0p333_0p333"],"t":5.405,"s":[0,0,100],"e":[100,100,100]},{"t":9.458984375}]}},"ao":0,"shapes":[{"d":1,"ty":"el","s":{"k":[16,16]},"p":{"k":[0,0]},"nm":"Ellipse Path 1","mn":"ADBE Vector Shape - Ellipse"},{"ty":"fl","fillEnabled":true,"c":{"k":[1,1,1,1]},"o":{"k":100},"nm":"Fill 1","mn":"ADBE Vector Graphic - Fill"}],"ip":0,"op":60,"st":0,"bm":0,"sr":1},{"ddd":0,"ind":53,"ty":4,"nm":"5","ks":{"o":{"k":100},"r":{"k":0},"p":{"k":[77.75,87,0]},"a":{"k":[0,0,0]},"s":{"k":[{"i":{"x":[0.667,0.667,0.667],"y":[1,1,0.667]},"o":{"x":[0.333,0.333,0.333],"y":[0,0,0.333]},"n":["0p667_1_0p333_0","0p667_1_0p333_0","0p667_0p667_0p333_0p333"],"t":5.405,"s":[0,0,100],"e":[100,100,100]},{"t":9.458984375}]}},"ao":0,"shapes":[{"d":1,"ty":"el","s":{"k":[16,16]},"p":{"k":[0,0]},"nm":"Ellipse Path 1","mn":"ADBE Vector Shape - Ellipse"},{"ty":"fl","fillEnabled":true,"c":{"k":[1,1,1,1]},"o":{"k":100},"nm":"Fill 1","mn":"ADBE Vector Graphic - Fill"}],"ip":0,"op":60,"st":0,"bm":0,"sr":1},{"ddd":0,"ind":54,"ty":4,"nm":"4","ks":{"o":{"k":100},"r":{"k":0},"p":{"k":[189.75,87,0]},"a":{"k":[0,0,0]},"s":{"k":[{"i":{"x":[0.667,0.667,0.667],"y":[1,1,0.667]},"o":{"x":[0.333,0.333,0.333],"y":[0,0,0.333]},"n":["0p667_1_0p333_0","0p667_1_0p333_0","0p667_0p667_0p333_0p333"],"t":5.405,"s":[0,0,100],"e":[100,100,100]},{"t":9.458984375}]}},"ao":0,"shapes":[{"d":1,"ty":"el","s":{"k":[16,16]},"p":{"k":[0,0]},"nm":"Ellipse Path 1","mn":"ADBE Vector Shape - Ellipse"},{"ty":"fl","fillEnabled":true,"c":{"k":[1,1,1,1]},"o":{"k":100},"nm":"Fill 1","mn":"ADBE Vector Graphic - Fill"}],"ip":0,"op":60,"st":0,"bm":0,"sr":1},{"ddd":0,"ind":55,"ty":4,"nm":"3","ks":{"o":{"k":100},"r":{"k":0},"p":{"k":[167.5,36.75,0]},"a":{"k":[0,0,0]},"s":{"k":[{"i":{"x":[0.667,0.667,0.667],"y":[1,1,0.667]},"o":{"x":[0.333,0.333,0.333],"y":[0,0,0.333]},"n":["0p667_1_0p333_0","0p667_1_0p333_0","0p667_0p667_0p333_0p333"],"t":5.405,"s":[0,0,100],"e":[100,100,100]},{"t":9.458984375}]}},"ao":0,"shapes":[{"d":1,"ty":"el","s":{"k":[16,16]},"p":{"k":[0,0]},"nm":"Ellipse Path 1","mn":"ADBE Vector Shape - Ellipse"},{"ty":"fl","fillEnabled":true,"c":{"k":[1,1,1,1]},"o":{"k":100},"nm":"Fill 1","mn":"ADBE Vector Graphic - Fill"}],"ip":0,"op":60,"st":0,"bm":0,"sr":1},{"ddd":0,"ind":56,"ty":4,"nm":"2","ks":{"o":{"k":100},"r":{"k":0},"p":{"k":[100.75,36.75,0]},"a":{"k":[0,0,0]},"s":{"k":[{"i":{"x":[0.667,0.667,0.667],"y":[1,1,0.667]},"o":{"x":[0.333,0.333,0.333],"y":[0,0,0.333]},"n":["0p667_1_0p333_0","0p667_1_0p333_0","0p667_0p667_0p333_0p333"],"t":5.405,"s":[0,0,100],"e":[100,100,100]},{"t":9.458984375}]}},"ao":0,"shapes":[{"d":1,"ty":"el","s":{"k":[16,16]},"p":{"k":[0,0]},"nm":"Ellipse Path 1","mn":"ADBE Vector Shape - Ellipse"},{"ty":"fl","fillEnabled":true,"c":{"k":[1,1,1,1]},"o":{"k":100},"nm":"Fill 1","mn":"ADBE Vector Graphic - Fill"}],"ip":0,"op":60,"st":0,"bm":0,"sr":1},{"ddd":0,"ind":57,"ty":4,"nm":"1","ks":{"o":{"k":100},"r":{"k":0},"p":{"k":[133.5,80.25,0]},"a":{"k":[0,0,0]},"s":{"k":[{"i":{"x":[0.667,0.667,0.667],"y":[1,1,0.667]},"o":{"x":[0.333,0.333,0.333],"y":[0,0,0.333]},"n":["0p667_1_0p333_0","0p667_1_0p333_0","0p667_0p667_0p333_0p333"],"t":0,"s":[0,0,100],"e":[100,100,100]},{"t":4.0537109375}]}},"ao":0,"shapes":[{"d":1,"ty":"el","s":{"k":[16,16]},"p":{"k":[0,0]},"nm":"Ellipse Path 1","mn":"ADBE Vector Shape - Ellipse"},{"ty":"fl","fillEnabled":true,"c":{"k":[1,1,1,1]},"o":{"k":100},"nm":"Fill 1","mn":"ADBE Vector Graphic - Fill"}],"ip":0,"op":60,"st":0,"bm":0,"sr":1}],"v":"4.5.3","ddd":0,"ip":0,"op":60,"fr":25,"w":284,"h":284}